Workbook

Sheet DASHBOARD_PRO
A1: ⚡ QA/QC PRO DASHBOARD — Control de Calidad Eléctrica & Instrumentación
A2: Especialista Responsable: Yesid Cruz — QA/QC Eléctrico & Instrumentación
A3: ⏱ Última actualización: | B3: Presione 🔄 ACTUALIZAR para registrar fecha
A6: 📋 TOTAL ACTIVIDADES | E6: 📊 AVANCE PONDERADO | I6: ⚠️ NCs ABIERTAS | M6: 📜 CERTIF. ENTREGADOS | Q6: 🔄 ACTUALIZAR DASHBOARD
A7: =CALC_DATA!B15 -> 22 | E7: =CALC_DATA!B18 -> 0.5784275 | I7: =CALC_DATA!B21 -> 2 | M7: =CALC_DATA!B22 -> 8
A8: ▼ Click 🔄 para actualizar | E8: ▼ Click 🔄 para actualizar | I8: ▼ Click 🔄 para actualizar | M8: ▼ Click 🔄 para actualizar
A11: 📁 AVANCE POR PROYECTO | I11: 📊 DISTRIBUCIÓN POR TIPO | P11: 📌 SEMÁFORO
A12: PROYECTO | B12: QC % | C12: QA % | D12: AVANCE TOT. | E12: ITEMS TOT. | F12: COMPLETOS | G12: ESTADO | I12: ACTIVIDAD | J12: TOTAL | K12: COMPLETADO | L12: % AVANCE | M12: ESTADO
A13: AZUFRE II | B13: =IFERROR(CALC_DATA!H3,0) -> 1 | C13: =IFERROR(CALC_DATA!G3,0) -> 1 | D13: =IFERROR(VLOOKUP("ECD22005_SISTEMA B-2880 AZUFRE II ETAPA 2",CONSOLIDADO!B:F,5,0),0) -> 1 | E13: =IFERROR(VLOOKUP("ECD22005_SISTEMA B-2880 AZUFRE II ETAPA 2",CONSOLIDADO!B:C,2,0),0) -> 8 | F13: =IFERROR(VLOOKUP("ECD22005_SISTEMA B-2880 AZUFRE II ETAPA 2",CONSOLIDADO!B:D,3,0),0) -> 8 | G13: =IF(D13>=0.9,"✅ Verde",IF(D13>=0.7,"⚠️ Amarillo","🔴 Rojo")) -> ✅ Verde | I13: INSTALACION | J13: =IFERROR(SUMPRODUCT((MASTER_ACTIVIDADES!C$3:C$198=I13)*(UPPER(MASTER_ACTIVIDADES!M$3:M$198)="SI")*MASTER_ACTIVIDADES!I$3:I$198),0) -> 96 | K13: =IFERROR(SUMPRODUCT((MASTER_ACTIVIDADES!C$3:C$198=I13)*(UPPER(MASTER_ACTIVIDADES!M$3:M$198)="SI")*(MASTER_ACTIVIDADES!N$3:N$198="Completo")*MASTER_ACTIVIDADES!I$3:I$198),0) -> 10 | L13: =IFERROR(K13/J13,0) -> 0.10416667 | M13: =IF(J13=0,"—",IF(L13>=0.9,"✅",IF(L13>=0.7,"⚠️","🔴"))) -> 🔴 | P13: ✅ VERDE | Q13: Avance ≥ 90%
A14: NUEVOLABORATORIO | B14: =IFERROR(CALC_DATA!H4,0) -> 0 | C14: =IFERROR(CALC_DATA!G4,0) -> 0 | D14: =IFERROR(VLOOKUP("ECD17011_NUEVOLABORATORIO GRB",CONSOLIDADO!B:F,5,0),0) -> 0 | E14: =IFERROR(VLOOKUP("ECD17011_NUEVOLABORATORIO GRB",CONSOLIDADO!B:C,2,0),0) -> 2 | F14: =IFERROR(VLOOKUP("ECD17011_NUEVOLABORATORIO GRB",CONSOLIDADO!B:D,3,0),0) -> 0 | G14: =IF(D14>=0.9,"✅ Verde",IF(D14>=0.7,"⚠️ Amarillo","🔴 Rojo")) -> 🔴 Rojo | I14: PRUEBAS | J14: =IFERROR(SUMPRODUCT((MASTER_ACTIVIDADES!C$3:C$198=I14)*(UPPER(MASTER_ACTIVIDADES!M$3:M$198)="SI")*MASTER_ACTIVIDADES!I$3:I$198),0) -> 80 | K14: =IFERROR(SUMPRODUCT((MASTER_ACTIVIDADES!C$3:C$198=I14)*(UPPER(MASTER_ACTIVIDADES!M$3:M$198)="SI")*(MASTER_ACTIVIDADES!N$3:N$198="Completo")*MASTER_ACTIVIDADES!I$3:I$198),0) -> 28 | L14: =IFERROR(K14/J14,0) -> 0.35 | M14: =IF(J14=0,"—",IF(L14>=0.9,"✅",IF(L14>=0.7,"⚠️","🔴"))) -> 🔴 | P14: ⚠️ AMARILLO | Q14: Avance 70–89%
A15: LBCC 10PPM | B15: =IFERROR(CALC_DATA!H5,0) -> 0.030263158 | C15: =IFERROR(CALC_DATA!G5,0) -> 0.33333333 | D15: =IFERROR(VLOOKUP("ECD20005_LINEA BASE CALIDAD DE COMBUSTIBLE 10 PPM",CONSOLIDADO!B:F,5,0),0) -> 0.19557416 | E15: =IFERROR(VLOOKUP("ECD20005_LINEA BASE CALIDAD DE COMBUSTIBLE 10 PPM",CONSOLIDADO!B:C,2,0),0) -> 12 | F15: =IFERROR(VLOOKUP("ECD20005_LINEA BASE CALIDAD DE COMBUSTIBLE 10 PPM",CONSOLIDADO!B:D,3,0),0) -> 2 | G15: =IF(D15>=0.9,"✅ Verde",IF(D15>=0.7,"⚠️ Amarillo","🔴 Rojo")) -> 🔴 Rojo | I15: DESINSTALACION | J15: =IFERROR(SUMPRODUCT((MASTER_ACTIVIDADES!C$3:C$198=I15)*(UPPER(MASTER_ACTIVIDADES!M$3:M$198)="SI")*MASTER_ACTIVIDADES!I$3:I$198),0) -> 21 | K15: =IFERROR(SUMPRODUCT((MASTER_ACTIVIDADES!C$3:C$198=I15)*(UPPER(MASTER_ACTIVIDADES!M$3:M$198)="SI")*(MASTER_ACTIVIDADES!N$3:N$198="Completo")*MASTER_ACTIVIDADES!I$3:I$198),0) -> 0 | L15: =IFERROR(K15/J15,0) -> 0 | M15: =IF(J15=0,"—",IF(L15>=0.9,"✅",IF(L15>=0.7,"⚠️","🔴"))) -> 🔴 | P15: 🔴 ROJO | Q15: Avance < 70%
I16: PLAN DE CALIDAD | J16: =IFERROR(SUMPRODUCT((MASTER_ACTIVIDADES!C$3:C$198=I16)*(UPPER(MASTER_ACTIVIDADES!M$3:M$198)="SI")*MASTER_ACTIVIDADES!I$3:I$198),0) -> 5 | K16: =IFERROR(SUMPRODUCT((MASTER_ACTIVIDADES!C$3:C$198=I16)*(UPPER(MASTER_ACTIVIDADES!M$3:M$198)="SI")*(MASTER_ACTIVIDADES!N$3:N$198="Completo")*MASTER_ACTIVIDADES!I$3:I$198),0) -> 2 | L16: =IFERROR(K16/J16,0) -> 0.4 | M16: =IF(J16=0,"—",IF(L16>=0.9,"✅",IF(L16>=0.7,"⚠️","🔴"))) -> 🔴
I17: ITP | J17: =IFERROR(SUMPRODUCT((MASTER_ACTIVIDADES!C$3:C$198=I17)*(UPPER(MASTER_ACTIVIDADES!M$3:M$198)="SI")*MASTER_ACTIVIDADES!I$3:I$198),0) -> 5 | K17: =IFERROR(SUMPRODUCT((MASTER_ACTIVIDADES!C$3:C$198=I17)*(UPPER(MASTER_ACTIVIDADES!M$3:M$198)="SI")*(MASTER_ACTIVIDADES!N$3:N$198="Completo")*MASTER_ACTIVIDADES!I$3:I$198),0) -> 2 | L17: =IFERROR(K17/J17,0) -> 0.4 | M17: =IF(J17=0,"—",IF(L17>=0.9,"✅",IF(L17>=0.7,"⚠️","🔴"))) -> 🔴
A18: 📅 CUMPLIMIENTO PLAN SEMANAL | I18: 📜 RESUMEN CERTIFICADOS | P18: 📊 KPIs ADICIONALES
A19: SEMANA | B19: PROGRAMADO | C19: EJECUTADO | D19: DESVIACIÓN | E19: % CUMPLIM. | F19: ALERTA | I19: PROYECTO | J19: TIPO | K19: PROGR. | L19: ENTREGADO | M19: % AVANCE | N19: ESTADO
A20: =CALC_DATA!D15 -> S24 | B20: =IFERROR(SUMIF(PLAN_SEMANAL!C$3:C$200,A20,PLAN_SEMANAL!E$3:E$200),0) -> 2 | C20: =IFERROR(SUMIF(PLAN_SEMANAL!C$3:C$200,A20,PLAN_SEMANAL!F$3:F$200),0) -> 1 | D20: =C20-B20 -> -1 | E20: =IFERROR(C20/B20,0) -> 0.5 | F20: =IF(B20=0,"➖ Sin datos",IF(E20>=0.9,"✅ Cumplido",IF(E20>=0.7,"⚠️ Parcial","🔴 Crítico"))) -> 🔴 Crítico | I20: AZUFRE II | J20: Cert. Calibracion | K20: =SUMIFS('CERTIFICADOS'!F:F, 'CERTIFICADOS'!A:A,"CERT-001-AZUFRE-CALIBRACION*",'CERTIFICADOS'!C:C, "Cert. Calibración") -> 9 | L20: =SUMIFS('CERTIFICADOS'!G:G, 'CERTIFICADOS'!A:A,"CERT-001-AZUFRE-CALIBRACION*",'CERTIFICADOS'!C:C, "Cert. Calibración") -> 9 | M20: =IFERROR(L20/K20,0) -> 1 | N20: =IF(K20=0,"⏳ Pendiente",IF(L20>=K20,"✅ Completo","🔄 Parcial")) -> ✅ Completo | P20: NC Registradas | R20: =IFERROR(COUNTIF('REGISTRO_NC'!I$3:I$201,"🔴 Abierta"),0) -> 2
A21: =CALC_DATA!D16 -> S23 | B21: =IFERROR(SUMIF(PLAN_SEMANAL!C$3:C$200,A21,PLAN_SEMANAL!E$3:E$200),0) -> 2 | C21: =IFERROR(SUMIF(PLAN_SEMANAL!C$3:C$200,A21,PLAN_SEMANAL!F$3:F$200),0) -> 0 | D21: =C21-B21 -> -2 | E21: =IFERROR(C21/B21,0) -> 0 | F21: =IF(B21=0,"➖ Sin datos",IF(E21>=0.9,"✅ Cumplido",IF(E21>=0.7,"⚠️ Parcial","🔴 Crítico"))) -> 🔴 Crítico | I21: AZUFRE II | J21: Conformidad | K21: =SUMIFS('CERTIFICADOS'!F:F, 'CERTIFICADOS'!A:A,"CERT-002-C-AZUFRE-MATERIALES*",'CERTIFICADOS'!C:C, "Conformidad Materiales") -> 10 | L21: =SUMIFS('CERTIFICADOS'!G:G, 'CERTIFICADOS'!A:A,"CERT-002-C-AZUFRE-MATERIALES*",'CERTIFICADOS'!C:C, "Conformidad Materiales") -> 10 | M21: =IFERROR(L21/K21,0) -> 1 | N21: =IF(K21=0,"⏳ Pendiente",IF(L21>=K21,"✅ Completo","🔄 Parcial")) -> ✅ Completo | P21: Semanas con datos | R21: =IFERROR(COUNTIF(PLAN_SEMANAL!C$3:C$200,"S*"),0) -> 9
A22: =CALC_DATA!D17 -> S23 | B22: =IFERROR(SUMIF(PLAN_SEMANAL!C$3:C$200,A22,PLAN_SEMANAL!E$3:E$200),0) -> 2 | C22: =IFERROR(SUMIF(PLAN_SEMANAL!C$3:C$200,A22,PLAN_SEMANAL!F$3:F$200),0) -> 0 | D22: =C22-B22 -> -2 | E22: =IFERROR(C22/B22,0) -> 0 | F22: =IF(B22=0,"➖ Sin datos",IF(E22>=0.9,"✅ Cumplido",IF(E22>=0.7,"⚠️ Parcial","🔴 Crítico"))) -> 🔴 Crítico | I22: NUEVOLAB | J22: Cert. Calibracion | K22: =SUMIFS('CERTIFICADOS'!F:F, 'CERTIFICADOS'!A:A,"CERT-001-NUEVOLAB-CALIBRACION*",'CERTIFICADOS'!C:C, "Cert. Calibración") -> 3 | L22: =SUMIFS('CERTIFICADOS'!G:G, 'CERTIFICADOS'!A:A,"CERT-001-NUEVOLAB-CALIBRACION*",'CERTIFICADOS'!C:C, "Cert. Calibración") -> 1 | M22: =IFERROR(L22/K22,0) -> 0.33333333 | N22: =IF(K22=0,"⏳ Pendiente",IF(L22>=K22,"✅ Completo","🔄 Parcial")) -> 🔄 Parcial | P22: Proyectos Activos | R22: =IFERROR(COUNTIF(CONSOLIDADO!F3:F12,">0"),0) -> 2
A23: =CALC_DATA!D18 -> S24 | B23: =IFERROR(SUMIF(PLAN_SEMANAL!C$3:C$200,A23,PLAN_SEMANAL!E$3:E$200),0) -> 2 | C23: =IFERROR(SUMIF(PLAN_SEMANAL!C$3:C$200,A23,PLAN_SEMANAL!F$3:F$200),0) -> 1 | D23: =C23-B23 -> -1 | E23: =IFERROR(C23/B23,0) -> 0.5 | F23: =IF(B23=0,"➖ Sin datos",IF(E23>=0.9,"✅ Cumplido",IF(E23>=0.7,"⚠️ Parcial","🔴 Crítico"))) -> 🔴 Crítico | I23: NUEVOLAB | J23: Conformidad | K23: =SUMIFS('CERTIFICADOS'!F:F, 'CERTIFICADOS'!A:A,"CERT-002-C-NUEVOLAB-MATERIALES*",'CERTIFICADOS'!C:C, "Conformidad Materiales") -> 3 | L23: =SUMIFS('CERTIFICADOS'!G:G, 'CERTIFICADOS'!A:A,"CERT-002-C-NUEVOLAB-MATERIALES*",'CERTIFICADOS'!C:C, "Conformidad Materiales") -> 0 | M23: =IFERROR(L23/K23,0) -> 0 | N23: =IF(K23=0,"⏳ Pendiente",IF(L23>=K23,"✅ Completo","🔄 Parcial")) -> 🔄 Parcial | P23: Responsables | R23: =IFERROR(SUMPRODUCT(1/COUNTIF(MASTER_ACTIVIDADES!J$3:J$198,MASTER_ACTIVIDADES!J$3:J$198)*(MASTER_ACTIVIDADES!J$3:J$198<>"")),0) -> 0
A24: =CALC_DATA!D19 -> S0 | B24: =IFERROR(SUMIF(PLAN_SEMANAL!C$3:C$200,A24,PLAN_SEMANAL!E$3:E$200),0) -> 0 | C24: =IFERROR(SUMIF(PLAN_SEMANAL!C$3:C$200,A24,PLAN_SEMANAL!F$3:F$200),0) -> 0 | D24: =C24-B24 -> 0 | E24: =IFERROR(C24/B24,0) -> 0 | F24: =IF(B24=0,"➖ Sin datos",IF(E24>=0.9,"✅ Cumplido",IF(E24>=0.7,"⚠️ Parcial","🔴 Crítico"))) -> ➖ Sin datos | I24: LBCC 10PPM | J24: Cert. Calibracion | K24: =SUMIFS('CERTIFICADOS'!F:F, 'CERTIFICADOS'!A:A,"CERT-001-LBCC-CALIBRACION*",'CERTIFICADOS'!C:C, "Cert. Calibración") -> 3 | L24: =SUMIFS('CERTIFICADOS'!G:G, 'CERTIFICADOS'!A:A,"CERT-001-LBCC-CALIBRACION*",'CERTIFICADOS'!C:C, "Cert. Calibración") -> 1 | M24: =IFERROR(L24/K24,0) -> 0.33333333 | N24: =IF(K24=0,"⏳ Pendiente",IF(L24>=K24,"✅ Completo","🔄 Parcial")) -> 🔄 Parcial
A25: =CALC_DATA!D20 -> S0 | B25: =IFERROR(SUMIF(PLAN_SEMANAL!C$3:C$200,A25,PLAN_SEMANAL!E$3:E$200),0) -> 0 | C25: =IFERROR(SUMIF(PLAN_SEMANAL!C$3:C$200,A25,PLAN_SEMANAL!F$3:F$200),0) -> 0 | D25: =C25-B25 -> 0 | E25: =IFERROR(C25/B25,0) -> 0 | F25: =IF(B25=0,"➖ Sin datos",IF(E25>=0.9,"✅ Cumplido",IF(E25>=0.7,"⚠️ Parcial","🔴 Crítico"))) -> ➖ Sin datos | I25: LBCC 10PPM | J25: Conformidad | K25: =SUMIFS('CERTIFICADOS'!F:F, 'CERTIFICADOS'!A:A,"CERT-002-LBCC-MATERIALES*",'CERTIFICADOS'!C:C, "Conformidad Materiales") -> 4 | L25: =SUMIFS('CERTIFICADOS'!G:G, 'CERTIFICADOS'!A:A,"CERT-002-LBCC-MATERIALES*",'CERTIFICADOS'!C:C, "Conformidad Materiales") -> 4 | M25: =IFERROR(L25/K25,0) -> 1 | N25: =IF(K25=0,"⏳ Pendiente",IF(L25>=K25,"✅ Completo","🔄 Parcial")) -> ✅ Completo
A27: 📈 ZONA DE GRÁFICOS GERENCIALES — QA vs QC por Proyecto | Desempeño Semanal
A28: PROYECTO | B28: QC % | C28: QA % | F28: SEMANA | G28: PROGRAMADO | H28: EJECUTADO
A29: AZUFRE II | B29: =IFERROR(CALC_DATA!H3,0) -> 1 | C29: =IFERROR(CALC_DATA!G3,0) -> 1 | F29: S21 | G29: =IFERROR(CALC_DATA!E15,0) -> 0 | H29: =IFERROR(CALC_DATA!F15,0) -> 0
A30: NUEVOLABORATORIO | B30: =IFERROR(CALC_DATA!H4,0) -> 0 | C30: =IFERROR(CALC_DATA!G4,0) -> 0 | F30: S22 | G30: =IFERROR(CALC_DATA!E16,0) -> 0 | H30: =IFERROR(CALC_DATA!F16,0) -> 0
A31: LBCC 10PPM | B31: =IFERROR(CALC_DATA!H5,0) -> 0.030263158 | C31: =IFERROR(CALC_DATA!G5,0) -> 0.33333333 | F31: S23 | G31: =IFERROR(CALC_DATA!E17,0) -> 2 | H31: =IFERROR(CALC_DATA!F17,0) -> 0
F32: S24 | G32: =IFERROR(CALC_DATA!E18,0) -> 2 | H32: =IFERROR(CALC_DATA!F18,0) -> 1
F33: S25 | G33: =IFERROR(CALC_DATA!E19,0) -> 0 | H33: =IFERROR(CALC_DATA!F19,0) -> 0
F34: S26 | G34: =IFERROR(CALC_DATA!E20,0) -> 0 | H34: =IFERROR(CALC_DATA!F20,0) -> 0

Sheet MASTER_ACTIVIDADES
A1: ⚙️ BASE DE DATOS MAESTRA — ACTIVIDADES QA/QC | Especialista: Yesid Cruz
A2: ID | B2: TIPO | C2: ACTIVIDAD | D2: SUBACTIVIDAD | E2: ESPECIALIDAD | F2: PROYECTO | G2: ODS | H2: PESO (%) | I2: CANTIDAD TOTAL | J2: RESPONSABLE | K2: NORMA | L2: COMENTARIOS | M2: APLICA | N2: ESTADO | O2: Comentarios2
A3: QA-001 | B3: QA | C3: PLAN DE CALIDAD | D3: Revision del plan | E3: Eléctrica | F3: ECD22005_SISTEMA B-2880 AZUFRE II ETAPA 2 | G3: ODS-016 | H3: 6 | I3: 1 | J3: Yesid Cruz | K3: ISO 9001 | L3: Plan aprobado | M3: SI | N3: Completo
A4: QA-002 | B4: QA | C4: ITP | D4: Revision/Aprobacion | E4: Eléctrica | F4: ECD22005_SISTEMA B-2880 AZUFRE II ETAPA 2 | G4: ODS-016 | H4: 8 | I4: 1 | J4: Yesid Cruz | K4: RETIE | L4: ITP aprobado | M4: SI | N4: Completo
A5: QA-003 | B5: QA | C5: DOSSIER | D5: Instalacion De bandejas | E5: Eléctrica | F5: ECD22005_SISTEMA B-2880 AZUFRE II ETAPA 2 | G5: ODS-016 | H5: 10 | I5: 1 | J5: Yesid Cruz | K5: RETIE | L5: ITP aprobado | M5: SI | N5: Completo
A6: QA-004 | B6: QA | C6: INSPECCION RUTINA | D6: Revisión documental | E6: Documental | F6: ECD22005_SISTEMA B-2880 AZUFRE II ETAPA 2 | G6: ODS-016 | H6: 0 | I6: 0 | J6: Yesid Cruz | K6: ISO 9001 | L6: Auditoría OK
A7: QA-005 | B7: QA | C7: NCR-VQA-PNC | D7: Seguimiento | E7: Documental | F7: ECD22005_SISTEMA B-2880 AZUFRE II ETAPA 2 | G7: ODS-016 | H7: 0 | I7: 0 | J7: Yesid Cruz | K7: RETIE Art.35 | L7: Pendiente 2 motores
A8: QA-006 | B8: QA | C8: CERTIFICADOS DE CALIBRACION | D8: Verificacion | E8: Eléctrica | F8: ECD22005_SISTEMA B-2880 AZUFRE II ETAPA 2 | G8: ODS-016 | H8: 10 | I8: 3 | J8: Yesid Cruz | K8: NTC 2050 | L8: OK | M8: SI | N8: Completo
A9: QA-007 | B9: QA | C9: CERTIFICADOS MATERIALES/EQUIPOS | D9: Verificacion | E9: Eléctrica | F9: ECD22005_SISTEMA B-2880 AZUFRE II ETAPA 2 | G9: ODS-016 | H9: 10 | I9: 6 | J9: Yesid Cruz | K9: OIML R 111 | L9: Cert. emitidos | M9: SI | N9: Completo
A10: QC-001 | B10: QC | C10: INSTALACION | D10: Instalacion de equipos | E10: Eléctrica | F10: ECD22005_SISTEMA B-2880 AZUFRE II ETAPA 2 | G10: ODS-016 | H10: 10 | I10: 6 | J10: Yesid Cruz | K10: ISO 9001 | L10: En revisión | M10: SI | N10: Completo
A11: QC-002 | B11: QC | C11: PRUEBAS | D11: Pruebas de Aislamiento | E11: Eléctrica | F11: ECD22005_SISTEMA B-2880 AZUFRE II ETAPA 2 | G11: ODS-016 | H11: 10 | I11: 24 | J11: Yesid Cruz | K11: ISA S5.1 | L11: ITP aprobado | M11: SI | N11: Completo
A12: QC-003 | B12: QC | C12: PRUEBAS | D12: Pruebas de SPT | E12: Eléctrica | F12: ECD22005_SISTEMA B-2880 AZUFRE II ETAPA 2 | G12: ODS-016 | H12: 12 | I12: 2 | J12: Yesid Cruz | K12: RETIE Art.35 | L12: En proceso | M12: SI | N12: Completo
A13: QC-004 | B13: QC | C13: INSTALACION | D13: Instalacion de bandejas porta cables | E13: Eléctrica | F13: ECD22005_SISTEMA B-2880 AZUFRE II ETAPA 2 | G13: ODS-016 | H13: 12 | I13: 2 | J13: Yesid Cruz | K13: NTC 2050 | L13: Programado S22 | M13: SI | N13: Completo
A14: QC-005 | B14: QC | C14: INSTALACION | D14: Instalacion Bancoductos | E14: Eléctrica | F14: ECD22005_SISTEMA B-2880 AZUFRE II ETAPA 2 | G14: ODS-016 | H14: 12 | I14: 2 | J14: Yesid Cruz | K14: OIML R 111 | L14: Programado S23 | M14: SI | N14: Completo
A15: QC-006 | B15: QC | C15: PRESERVACION | D15: Preservacion de equipos | E15: Electrica | F15: ECD22005_SISTEMA B-2880 AZUFRE II ETAPA 2 | G15: ODS-016 | J15: Yesid Cruz
A16: QC-007 | B16: QC | C16: DESINSTALACION | D16: Desmantelamiento | E16: Electrica | F16: ECD22005_SISTEMA B-2880 AZUFRE II ETAPA 2 | G16: ODS-016
A17: QA-001 | B17: QA | C17: PLAN DE CALIDAD | D17: Revision del plan | E17: Eléctrica | F17: ECD20005_LINEA BASE CALIDAD DE COMBUSTIBLE 10 PPM | G17: ODS-20 | H17: 8 | I17: 1 | J17: Yesid Cruz | K17: RETIE | L17: En ajuste | M17: SI | N17: Completo
A18: QA-002 | B18: QA | C18: ITP | D18: Revision/Aprobacion | E18: Eléctrica | F18: ECD20005_LINEA BASE CALIDAD DE COMBUSTIBLE 10 PPM | G18: ODS-20 | H18: 8 | I18: 1 | J18: Yesid Cruz | K18: RETIE Art.35 | L18: OK 4 de 6 | M18: SI | N18: Completo
A19: QA-003 | B19: QA | C19: DOSSIER | D19: Revisión documental | E19: Eléctrica | F19: ECD20005_LINEA BASE CALIDAD DE COMBUSTIBLE 10 PPM | G19: ODS-20 | H19: 8 | I19: 1 | J19: Yesid Cruz | K19: NTC 2050 | L19: Programado S22 | M19: SI | N19: Asignado
A20: QA-004 | B20: QA | C20: INSPECCION RUTINA | D20: Revisión documental | E20: Eléctrica | F20: ECD20005_LINEA BASE CALIDAD DE COMBUSTIBLE 10 PPM | G20: ODS-20 | H20: 8 | I20: 1 | J20: Yesid Cruz | K20: OIML R 111 | L20: Programado S23 | M20: SI | N20: Asignado
A21: QA-005 | B21: QA | C21: NCR-VQA-PNC | D21: Seguimiento | E21: Eléctrica | F21: ECD20005_LINEA BASE CALIDAD DE COMBUSTIBLE 10 PPM | G21: ODS-20 | H21: 8 | I21: 0 | J21: Yesid Cruz | K21: OIML R 112 | L21: Programado S24 | M21: SI | N21: Asignado
A22: QA-006 | B22: QA | C22: CERTIFICADOS DE CALIBRACION | D22: Verificacion | E22: Eléctrica | F22: ECD20005_LINEA BASE CALIDAD DE COMBUSTIBLE 10 PPM | G22: ODS-20 | H22: 8 | I22: 3 | J22: Yesid Cruz | K22: OIML R 113 | L22: Programado S25 | M22: SI | N22: Asignado
A23: QA-007 | B23: QA | C23: CERTIFICADOS MATERIALES/EQUIPOS | D23: Verificacion | E23: Eléctrica | F23: ECD20005_LINEA BASE CALIDAD DE COMBUSTIBLE 10 PPM | G23: ODS-20 | H23: 8 | I23: 5 | J23: Yesid Cruz | K23: OIML R 114 | L23: Programado S26 | M23: SI | N23: Asignado | O23: Tableros proteccion catodica, luminarias, bandejas, tuberia conduit, SPT
A24: QC-001 | B24: QC | C24: INSTALACION | D24: Instalacion de equipos | E24: Eléctrica | F24: ECD20005_LINEA BASE CALIDAD DE COMBUSTIBLE 10 PPM | G24: ODS-20 | H24: 8 | I24: 15 | J24: Yesid Cruz | K24: OIML R 115 | L24: Programado S27 | M24: SI | N24: Asignado
A25: QC-002 | B25: QC | C25: PRUEBAS | D25: Pruebas de Aislamiento | E25: Eléctrica | F25: ECD20005_LINEA BASE CALIDAD DE COMBUSTIBLE 10 PPM | G25: ODS-20 | H25: 7 | I25: 39 | J25: Yesid Cruz | K25: OIML R 116 | L25: Programado S28 | M25: SI | N25: Asignado
A26: QC-003 | B26: QC | C26: PRUEBAS | D26: Pruebas de SPT | E26: Eléctrica | F26: ECD20005_LINEA BASE CALIDAD DE COMBUSTIBLE 10 PPM | G26: ODS-20 | H26: 7 | I26: 7 | J26: Yesid Cruz | K26: OIML R 117 | L26: Programado S29 | M26: SI | N26: Asignado
A27: QC-004 | B27: QC | C27: INSTALACION | D27: Instalacion de bandejas porta cables | E27: Eléctrica | F27: ECD20005_LINEA BASE CALIDAD DE COMBUSTIBLE 10 PPM | G27: ODS-20 | H27: 7 | I27: 8 | J27: Yesid Cruz | K27: OIML R 118 | L27: Programado S30 | M27: SI | N27: Asignado
A28: QC-005 | B28: QC | C28: INSTALACION | D28: Instalacion Bancoductos | E28: Eléctrica | F28: ECD20005_LINEA BASE CALIDAD DE COMBUSTIBLE 10 PPM | G28: ODS-20 | H28: 7 | I28: 22 | J28: Yesid Cruz | K28: OIML R 119 | L28: Programado S31 | M28: SI | N28: Asignado
A29: QC-006 | B29: QC | C29: PRESERVACION | D29: Preservacion de equipos | E29: Electrica | F29: ECD20005_LINEA BASE CALIDAD DE COMBUSTIBLE 10 PPM | G29: ODS-020 | H29: 4 | I29: 9 | J29: Albert Trujillo | L29: En Ejecucion | M29: SI | N29: Asignado | O29: Motores de tanques
A30: QC-007 | B30: QC | C30: DESINSTALACION | D30: Desmantelamiento | E30: Electrica | F30: ECD20005_LINEA BASE CALIDAD DE COMBUSTIBLE 10 PPM | G30: ODS-020 | H30: 4 | I30: 19 | J30: Albert Trujillo | L30: En Ejecucion | M30: SI | N30: Asignado | O30: Motores y cables
A31: QA-001 | B31: QA | C31: PLAN DE CALIDAD | D31: Revision del plan | E31: Eléctrica | F31: ECD17011_NUEVOLABORATORIO GRB | G31: ODS-07 | H31: 0.079 | I31: 1 | J31: Yesid Cruz | K31: ISO 10005 | L31: Aprobado | M31: SI | N31: Asignado
A32: QA-002 | B32: QA | C32: ITP | D32: Revision/Aprobacion | E32: Electrica | F32: ECD17011_NUEVOLABORATORIO GRB | G32: ODS-07 | H32: 0.079 | I32: 1 | J32: Yesid Cruz | K32: ISO 10005 | L32: Aprobado | M32: SI | N32: Asignado
A33: QA-003 | B33: QA | C33: DOSSIER | D33: Revision/Aprobacion | E33: Electrica | F33: ECD17011_NUEVOLABORATORIO GRB | G33: ODS-07 | H33: 0.08 | I33: 1 | J33: Yesid Cruz | K33: GYQ | L33: Aprobado | M33: SI | N33: Asignado
A34: QA-004 | B34: QA | C34: INSPECCION RUTINA | D34: Revision documental | E34: Electrica | F34: ECD17011_NUEVOLABORATORIO GRB | G34: ODS-07 | H34: 0.08 | I34: 2 | J34: Yesid Cruz | K34: EDP | L34: Programado | M34: SI | N34: Asignado
A35: QA-005 | B35: QA | C35: NCR-VQA-PNC | D35: Seguimeinto | E35: Electrica | F35: ECD17011_NUEVOLABORATORIO GRB | G35: ODS-07 | H35: 0.08 | I35: 1 | J35: Yesid Cruz | K35: EDP | L35: Programado | M35: SI | N35: Asignado
A36: QA-006 | B36: QA | C36: CERTIFICADOS DE CALIBRACION | D36: Verificacion | E36: Electrica | F36: ECD17011_NUEVOLABORATORIO GRB | G36: ODS-07 | H36: 0.03 | I36: 3 | J36: Yesid Cruz | K36: EDP | L36: Programado | M36: SI | N36: Asignado
A37: QA-007 | B37: QA | C37: CERTIFICADOS MATERIALES/EQUIPOS | D37: Verificacion | E37: Eléctrica | F37: ECD17011_NUEVOLABORATORIO GRB | G37: ODS-07 | H37: 0.03 | I37: 2 | J37: Yesid Cruz | K37: EDP | L37: Programado | M37: SI | N37: Asignado
A38: QC-001 | B38: QC | C38: INSTALACION | D38: Instalacion de equipos | E38: Eléctrica | F38: ECD17011_NUEVOLABORATORIO GRB | G38: ODS-07 | H38: 0.03 | I38: 31 | J38: Yesid Cruz | K38: EDP | L38: Programado | M38: SI | N38: Asignado
A39: QC-002 | B39: QC | C39: PRUEBAS | D39: Pruebas de Aislamiento | E39: Eléctrica | F39: ECD17011_NUEVOLABORATORIO GRB | G39: ODS-07 | H39: 0.03 | I39: 2 | J39: Yesid Cruz | K39: EDP | L39: Programado | M39: SI | N39: Asignado
A40: QC-003 | B40: QC | C40: PRUEBAS | D40: Pruebas de SPT | E40: Eléctrica | F40: ECD17011_NUEVOLABORATORIO GRB | G40: ODS-07 | H40: 0.03 | I40: 2 | J40: Yesid Cruz | K40: EDP | L40: Programado | M40: SI | N40: Completo
A41: QC-004 | B41: QC | C41: INSTALACION | D41: Instalacion de bandejas porta cables | E41: Eléctrica | F41: ECD17011_NUEVOLABORATORIO GRB | G41: ODS-07 | H41: 0.03 | I41: 2 | J41: Yesid Cruz | K41: EDP | L41: Programado | M41: SI | N41: Asignado
A42: QC-005 | B42: QC | C42: INSTALACION | D42: Instalacion Bancoductos | E42: Eléctrica | F42: ECD17011_NUEVOLABORATORIO GRB | G42: ODS-07 | H42: 0.03 | I42: 2 | J42: Yesid Cruz | K42: EDP | L42: Programado | M42: SI | N42: Asignado
A43: QC-006 | B43: QC | C43: PRESERVACION | D43: Preservacion de equipos | E43: Electrica | F43: ECD17011_NUEVOLABORATORIO GRB | G43: ODS-07 | H43: 0.02 | I43: 2 | J43: Lenar Parra | L43: Programado | M43: SI | N43: Asignado
A44: QC-007 | B44: QC | C44: DESINSTALACION | D44: Desmantelamiento | E44: Electrica | F44: ECD17011_NUEVOLABORATORIO GRB | G44: ODS-07 | H44: 0.02 | I44: 0 | J44: Lenar Parra | L44: Programado
A45: QA-001 | B45: QA | C45: PLAN DE CALIDAD | D45: Revision del plan | E45: Eléctrica | F45: ECD17011_NUEVOLABORATORIO GRB | G45: CW23339 | H45: 0.079 | I45: 2 | J45: Yesid Cruz | K45: EDP | L45: Programado | M45: SI | N45: Asignado
A46: QA-002 | B46: QA | C46: ITP | D46: Revision/Aprobacion | E46: Electrica | F46: ECD17011_NUEVOLABORATORIO GRB | G46: CW23339 | H46: 0.079 | I46: 2 | J46: Yesid Cruz | K46: EDP | L46: Programado | M46: SI | N46: Asignado
A47: QA-003 | B47: QA | C47: DOSSIER | D47: Revision/Aprobacion | E47: Electrica | F47: ECD17011_NUEVOLABORATORIO GRB | G47: CW23339 | H47: 0.08 | I47: 2 | J47: Yesid Cruz | K47: EDP | L47: Programado | M47: SI | N47: Asignado
A48: QA-004 | B48: QA | C48: INSPECCION RUTINA | D48: Revision documental | E48: Electrica | F48: ECD17011_NUEVOLABORATORIO GRB | G48: CW23339 | H48: 0.08 | I48: 1 | J48: Yesid Cruz | K48: EDP | L48: Programado | M48: SI | N48: Asignado
A49: QA-005 | B49: QA | C49: NCR-VQA-PNC | D49: Seguimiento | E49: Electrica | F49: ECD17011_NUEVOLABORATORIO GRB | G49: CW23339 | H49: 0.08 | I49: 2 | J49: Yesid Cruz | K49: EDP | L49: Programado | M49: SI | N49: Asignado
A50: QA-006 | B50: QA | C50: CERTIFICADOS DE CALIBRACION | D50: Verificacion | E50: Electrica | F50: ECD17011_NUEVOLABORATORIO GRB | G50: CW23339 | H50: 0.03 | I50: 2 | J50: Yesid Cruz | K50: EDP | L50: Programado | M50: SI | N50: Asignado
A51: QA-007 | B51: QA | C51: CERTIFICADOS MATERIALES/EQUIPOS | D51: Verificacion | E51: Eléctrica | F51: ECD17011_NUEVOLABORATORIO GRB | G51: CW23339 | H51: 0.03 | I51: 3 | J51: Yesid Cruz | K51: EDP | L51: Programado | M51: SI | N51: Asignado
A52: QC-001 | B52: QC | C52: INSTALACION | D52: Instalacion de equipos | E52: Eléctrica | F52: ECD17011_NUEVOLABORATORIO GRB | G52: CW23339 | H52: 0.03 | I52: 2 | J52: Yesid Cruz | K52: EDP | L52: Programado | M52: SI | N52: Asignado
A53: QC-002 | B53: QC | C53: PRUEBAS | D53: Pruebas de Aislamiento | E53: Eléctrica | F53: ECD17011_NUEVOLABORATORIO GRB | G53: CW23339 | H53: 0.03 | I53: 2 | J53: Yesid Cruz | K53: EDP | L53: Programado | M53: SI | N53: Asignado
A54: QC-003 | B54: QC | C54: PRUEBAS | D54: Pruebas de SPT | E54: Eléctrica | F54: ECD17011_NUEVOLABORATORIO GRB | G54: CW23339 | H54: 0.03 | I54: 2 | J54: Yesid Cruz | K54: EDP | L54: Programado | M54: SI | N54: Asignado
A55: QC-004 | B55: QC | C55: INSTALACION | D55: Instalacion de bandejas porta cables | E55: Eléctrica | F55: ECD17011_NUEVOLABORATORIO GRB | G55: CW23339 | H55: 0.03 | I55: 2 | J55: Yesid Cruz | K55: EDP | L55: Programado | M55: SI | N55: Asignado
A56: QC-005 | B56: QC | C56: INSTALACION | D56: Instalacion Bancoductos | E56: Eléctrica | F56: ECD17011_NUEVOLABORATORIO GRB | G56: CW23339 | H56: 0.03 | I56: 2 | J56: Yesid Cruz | K56: EDP | L56: Programado | M56: SI | N56: Asignado
... A58: QC-007 | B58: QC | C58: DESINSTALACION | D58: Desmantelamiento | E58: Electrica | F58: ECD17011_NUEVOLABORATORIO GRB | G58: CW23339 | H58: 0.02 | I58: 2 | J58: Lineth Barroso | K58: EDP | L58: Programado | M58: SI | N58: Asignado

Sheet QC_DETALLE
A1: 🔍 DETALLE QC — Registros de Inspección y Pruebas | QA/QC PRO Dashboard — Yesid Cruz
A2: ID | B2: PROYECTO | C2: ESPECIALIDAD | D2: ELEMENTO | E2: ACTIVIDAD QC | F2: TAG | G2: TIPO ENSAYO | H2: PROGRAMADO | I2: EJECUTADO | J2: % AVANCE | K2: PENDIENTE
A3: QC-001 | B3: ECD22005_SISTEMA B-2880 AZUFRE II ETAPA 2 | C3: Eléctrica | D3: Tablero GIM | E3: Instalacion | F3: TDGIM | G3: Registro De Instalacion | H3: 1 | I3: 1 | J3: =IFERROR(I3/H3,0) -> 1 | K3: =H3-I3 -> 0
A4: QC-001 | B4: ECD22005_SISTEMA B-2880 AZUFRE II ETAPA 2 | C4: Eléctrica | D4: Ventilador | E4: Instalacion | F4: MU-2880 | G4: Registro de Instalacion | H4: 1 | I4: 1 | J4: =IFERROR(I4/H4,0) -> 1 | K4: =H4-I4 -> 0
A5: QC-002 | B5: ECD22005_SISTEMA B-2880 AZUFRE II ETAPA 2 | C5: Eléctrica | D5: Arrancador Suave | E5: Prueba de aislamiento | F5: PCC2882 | G5: Prueba | H5: 1 | I5: 1 | J5: =IFERROR(I5/H5,0) -> 1 | K5: =H5-I5 -> 0
A6: QC-002 | B6: ECD22005_SISTEMA B-2880 AZUFRE II ETAPA 2 | C6: Eléctrica | D6: Bomba Piscina de Azufre (Stand by) (MP-2887B) | E6: Prueba de aislamiento | F6: PCP2887B | G6: Prueba | H6: 1 | I6: 1 | J6: =IFERROR(I6/H6,0) -> 1 | K6: =H6-I6 -> 0
A7: QC-002 | B7: ECD22005_SISTEMA B-2880 AZUFRE II ETAPA 2 | C7: Eléctrica | D7: Bomba Aceite Compresor PCP-2882 | E7: Prueba de aislamiento | F7: PCP2882 | G7: Prueba | H7: 1 | I7: 1 | J7: =IFERROR(I7/H7,0) -> 1 | K7: =H7-I7 -> 0
A8: QC-002 | B8: ECD22005_SISTEMA B-2880 AZUFRE II ETAPA 2 | C8: Eléctrica | D8: Calentador Compresor | E8: Prueba de aislamiento | F8: PCE2882 | G8: Prueba | H8: 1 | I8: 1 | J8: =IFERROR(I8/H8,0) -> 1 | K8: =H8-I8 -> 0
A9: QC-002 | B9: ECD22005_SISTEMA B-2880 AZUFRE II ETAPA 2 | C9: Eléctrica | D9: ET218PMCCF01DN3C5 | E9: Prueba de aislamiento | F9: P2887B/ET218PMCCF01DN3C5(CCP2887B LCS1) | G9: Prueba | H9: 1 | I9: 1 | J9: =IFERROR(I9/H9,0) -> 1 | K9: =H9-I9 -> 0
A10: QC-002 | B10: ECD22005_SISTEMA B-2880 AZUFRE II ETAPA 2 | C10: Eléctrica | D10: ET218PMCCF01DN3C5 | E10: Prueba de aislamiento | F10: P2887B/ET218PMCCF01DN3C5(CCP2887B LCS2) | G10: Prueba | H10: 1 | I10: 1 | J10: =IFERROR(I10/H10,0) -> 1 | K10: =H10-I10 -> 0
A11: QC-002 | B11: ECD22005_SISTEMA B-2880 AZUFRE II ETAPA 2 | C11: Eléctrica | D11: ET218PMCCF01BN16P3 | E11: Prueba de aislamiento | F11: P2887A/ET218PMCCF01BN16P3 | G11: Prueba | H11: 1 | I11: 1 | J11: =IFERROR(I11/H11,0) -> 1 | K11: =H11-I11 -> 0
A12: QC-002 | B12: ECD22005_SISTEMA B-2880 AZUFRE II ETAPA 2 | C12: Eléctrica | D12: ET218PMCCF01CN4C5 | E12: Prueba de aislamiento | F12: P2882/ET218PMCCF01CN4C5 | G12: Prueba | H12: 1 | I12: 1 | J12: =IFERROR(I12/H12,0) -> 1 | K12: =H12-I12 -> 0
A13: QC-002 | B13: ECD22005_SISTEMA B-2880 AZUFRE II ETAPA 2 | C13: Eléctrica | D13: DC28802 | E13: Prueba de aislamiento | F13: ET218-ELP-02/DC28802 | G13: Prueba | H13: 1 | I13: 1 | J13: =IFERROR(I13/H13,0) -> 1 | K13: =H13-I13 -> 0
A14: QC-002 | B14: ECD22005_SISTEMA B-2880 AZUFRE II ETAPA 2 | C14: Eléctrica | D14: CPI28803 | E14: Prueba de aislamiento | F14: CPI28803 | G14: Prueba | H14: 1 | I14: 1 | J14: =IFERROR(I14/H14,0) -> 1 | K14: =H14-I14 -> 0
... A56: QC-001 | B56: ECD20005_LINEA BASE CALIDAD DE COMBUSTIBLE 10 PPM | C56: Eléctrica | D56: Tablero Electrico-Alumbrado | E56: Relocalizar | F56: 46DLP-1-4 | G56: Registro De Instalacion | H56: 1 | I56: 0 | J56: =IFERROR(I56/H56,0) -> 0 | K56: =H56-I56 -> 1
A57: QC-001 | B57: ECD20005_LINEA BASE CALIDAD DE COMBUSTIBLE 10 PPM | C57: Eléctrica | D57: Tablero Electrico-Proteccion Catodica | E57: Instalacion | G57: Registro De Instalacion | H57: 1 | I57: 0 | J57: =IFERROR(I57/H57,0) -> 0 | K57: =H57-I57 -> 1
A58: QC-001 | B58: ECD20005_LINEA BASE CALIDAD DE COMBUSTIBLE 10 PPM | C58: Eléctrica | D58: Tablero de cargas criticas | E58: Relocalizar | F58: 46DP-5 | G58: Registro De Instalacion | H58: 1 | I58: 0 | J58: =IFERROR(I58/H58,0) -> 0 | K58: =H58-I58 -> 1
A59: QC-002 | B59: ECD20005_LINEA BASE CALIDAD DE COMBUSTIBLE 10 PPM | C59: Eléctrica | D59: ALIMENTADOR DE POTENCIA MOTOR BOMBA DE SODA MP-4610A | E59: Prueba de aislamiento | F59: ALBT-MP4610A | G59: Prueba | H59: 1 | I59: 0 | J59: =IFERROR(I59/H59,0) -> 0 | K59: =H59-I59 -> 1
A60: QC-002 | B60: ECD20005_LINEA BASE CALIDAD DE COMBUSTIBLE 10 PPM | C60: Eléctrica | D60: TIERRA - ALIMENTADOR DE POTENCIA MOTOR BOMBA DE SODA MP-4610A | E60: Prueba de aislamiento | F60: ALBT-MP4610A | G60: Prueba | H60: 1 | I60: 0 | J60: =IFERROR(I60/H60,0) -> 0 | K60: =H60-I60 -> 1
A61: QC-002 | B61: ECD20005_LINEA BASE CALIDAD DE COMBUSTIBLE 10 PPM | C61: Eléctrica | D61: ALIMENTADOR DE CONTROL ELÉCTRICO MOTOR BOMBA DE SODA MP-4610A | E61: Prueba de aislamiento | F61: CTRL-MP4610A | G61: Prueba | H61: 1 | I61: 0 | J61: =IFERROR(I61/H61,0) -> 0 | K61: =H61-I61 -> 1
A62: QC-002 | B62: ECD20005_LINEA BASE CALIDAD DE COMBUSTIBLE 10 PPM | C62: Eléctrica | D62: ALIMENTADOR DE POTENCIA MOTOR BOMBA DE SODA MP-4610B | E62: Prueba de aislamiento | F62: ALBT-MP4610B | G62: Prueba | H62: 1 | I62: 0 | J62: =IFERROR(I62/H62,0) -> 0 | K62: =H62-I62 -> 1
A63: QC-002 | B63: ECD20005_LINEA BASE CALIDAD DE COMBUSTIBLE 10 PPM | C63: Eléctrica | D63: TIERRA - ALIMENTADOR DE POTENCIA MOTOR BOMBA DE SODA MP-4610B | E63: Prueba de aislamiento | F63: ALBT-MP4610B | G63: Prueba | H63: 1 | I63: 0 | J63: =IFERROR(I63/H63,0) -> 0 | K63: =H63-I63 -> 1
A64: QC-002 | B64: ECD20005_LINEA BASE CALIDAD DE COMBUSTIBLE 10 PPM | C64: Eléctrica | D64: ALIMENTADOR DE CONTROL ELÉCTRICO MOTOR BOMBA DE SODA MP-4610B | E64: Prueba de aislamiento | F64: CTRL-MP4610B | G64: Prueba | H64: 1 | I64: 0 | J64: =IFERROR(I64/H64,0) -> 0 | K64: =H64-I64 -> 1
A65: QC-002 | B65: ECD20005_LINEA BASE CALIDAD DE COMBUSTIBLE 10 PPM | C65: Eléctrica | D65: ALIMENTADOR DE POTENCIA MOTOR BOMBA DE SODA MP-4610C | E65: Prueba de aislamiento | F65: ALBT-MP4610C | G65: Prueba | H65: 1 | I65: 0 | J65: =IFERROR(I65/H65,0) -> 0 | K65: =H65-I65 -> 1
A66: QC-002 | B66: ECD20005_LINEA BASE CALIDAD DE COMBUSTIBLE 10 PPM | C66: Eléctrica | D66: TIERRA - ALIMENTADOR DE POTENCIA MOTOR BOMBA DE SODA MP-4610C | E66: Prueba de aislamiento | F66: ALBT-MP4610C | G66: Prueba | H66: 1 | I66: 0 | J66: =IFERROR(I66/H66,0) -> 0 | K66: =H66-I66 -> 1
A67: QC-002 | B67: ECD20005_LINEA BASE CALIDAD DE COMBUSTIBLE 10 PPM | C67: Eléctrica | D67: ALIMENTADOR DE CONTROL ELÉCTRICO MOTOR BOMBA DE SODA PM-4610C | E67: Prueba de aislamiento | F67: CTRL-MP4610C | G67: Prueba | H67: 1 | I67: 0 | J67: =IFERROR(I67/H67,0) -> 0 | K67: =H67-I67 -> 1
A68: QC-002 | B68: ECD20005_LINEA BASE CALIDAD DE COMBUSTIBLE 10 PPM | C68: Eléctrica | D68: ALIMENTADOR DE POTENCIA MOTOR BOMBA DE AGUA FRESCA MP-4612A | E68: Prueba de aislamiento | F68: ALBT-MP4612A | G68: Prueba | H68: 1 | I68: 0 | J68: =IFERROR(I68/H68,0) -> 0 | K68: =H68-I68 -> 1
A69: QC-002 | B69: ECD20005_LINEA BASE CALIDAD DE COMBUSTIBLE 10 PPM | C69: Eléctrica | D69: ALIMENTADOR DE CONTROL ELÉCTRICO MOTOR BOMBA DE AGUA FRESCA MP-4612A | E69: Prueba de aislamiento | F69: CTRL-MP4612A | G69: Prueba | H69: 1 | I69: 0 | J69: =IFERROR(I69/H69,0) -> 0 | K69: =H69-I69 -> 1
... A113: QC-005 | B113: ECD20005_LINEA BASE CALIDAD DE COMBUSTIBLE 10 PPM | C113: Eléctrica | D113: Tuberia Conduit | E113: Instalacion | F113: Casa Bombas | G113: Registro De Instalacion | H113: 22 | I113: 0 | J113: =IFERROR(I113/H113,0) -> 0 | K113: =H113-I113 -> 22
A114: QC-007 | B114: ECD20005_LINEA BASE CALIDAD DE COMBUSTIBLE 10 PPM | C114: Eléctrica | D114: Motores | E114: Desmantelamiento | G114: Registro de desmantelamiento | H114: 19 | I114: 1 | J114: =IFERROR(I114/H114,0) -> 0.052631579 | K114: =H114-I114 -> 18
A115: QA-001 | B115: ECD20005_LINEA BASE CALIDAD DE COMBUSTIBLE 10 PPM | C115: Electrica | D115: Revision del plan | E115: N/A | F115: N/A | G115: Revision del plan | H115: 1 | I115: 1 | J115: =IFERROR(I115/H115,0) -> 1 | K115: =H115-I115 -> 0
A116: QA-002 | B116: ECD20005_LINEA BASE CALIDAD DE COMBUSTIBLE 10 PPM | C116: Electrica | D116: Revision ITP | E116: N/A | F116: N/A | G116: Revision ITP | H116: 1 | I116: 1 | J116: =IFERROR(I116/H116,0) -> 1 | K116: =H116-I116 -> 0
A117: QA-003 | B117: ECD20005_LINEA BASE CALIDAD DE COMBUSTIBLE 10 PPM | C117: Electrica | D117: Revision del dossier | E117: N/A | F117: N/A | G117: Revision Dossier | H117: 1 | I117: 0 | J117: =IFERROR(I117/H117,0) -> 0 | K117: =H117-I117 -> 1
A118: QA-004 | B118: ECD20005_LINEA BASE CALIDAD DE COMBUSTIBLE 10 PPM | C118: Electrica | D118: Inspeccion de Rutina | E118: N/A | F118: N/A | G118: Formato A-B-C | H118: 1 | I118: 0 | J118: =IFERROR(I118/H118,0) -> 0 | K118: =H118-I118 -> 1
A119: QA-005 | B119: ECD20005_LINEA BASE CALIDAD DE COMBUSTIBLE 10 PPM | C119: Electrica | D119: NCR-VQA-PNC | E119: N/A | F119: N/A | G119: Cierre de hallazgos | H119: 0 | I119: 0 | J119: =IFERROR(I119/H119,0) -> 0 | K119: =H119-I119 -> 0
A120: QA-006 | B120: ECD20005_LINEA BASE CALIDAD DE COMBUSTIBLE 10 PPM | C120: Electrica | D120: Certificado de calibracon Megohmetro | E120: N/A | F120: N/A | G120: Certificado | H120: 1 | I120: 0 | J120: =IFERROR(I120/H120,0) -> 0 | K120: =H120-I120 -> 1
A121: QA-006 | B121: ECD20005_LINEA BASE CALIDAD DE COMBUSTIBLE 10 PPM | C121: Electrica | D121: Certificado de calibracion Multimetro | E121: N/A | F121: N/A | G121: Certificado | H121: 1 | I121: 0 | J121: =IFERROR(I121/H121,0) -> 0 | K121: =H121-I121 -> 1
A122: QA-006 | B122: ECD20005_LINEA BASE CALIDAD DE COMBUSTIBLE 10 PPM | C122: Electrica | D122: Certificado de calibracion de telurometro | E122: N/A | F122: N/A | G122: Certificado | H122: 1 | I122: 0 | J122: =IFERROR(I122/H122,0) -> 0 | K122: =H122-I122 -> 1
A123: QA-007 | B123: ECD20005_LINEA BASE CALIDAD DE COMBUSTIBLE 10 PPM | C123: Electrica | D123: Certificado de materiales/Bandejas | E123: N/A | F123: N/A | G123: Certificado de conformidad | H123: 1 | I123: 0 | J123: =IFERROR(I123/H123,0) -> 0 | K123: =H123-I123 -> 1
A124: QA-007 | B124: ECD20005_LINEA BASE CALIDAD DE COMBUSTIBLE 10 PPM | C124: Electrica | D124: Certificado de materiales/Tuberia conduit | E124: N/A | F124: N/A | G124: Certificado de conformidad | H124: 1 | I124: 0 | J124: =IFERROR(I124/H124,0) -> 0 | K124: =H124-I124 -> 1
A125: QA-007 | B125: ECD20005_LINEA BASE CALIDAD DE COMBUSTIBLE 10 PPM | C125: Electrica | D125: Certificado de materiales/Cable SPT | E125: N/A | F125: N/A | G125: Certificado de conformidad | H125: 1 | I125: 0 | J125: =IFERROR(I125/H125,0) -> 0 | K125: =H125-I125 -> 1
A126: QA-007 | B126: ECD20005_LINEA BASE CALIDAD DE COMBUSTIBLE 10 PPM | C126: Electrica | D126: Certificado de materiales/Proteccion catodica | E126: N/A | F126: N/A | G126: Certificado de conformidad | H126: 1 | I126: 0 | J126: =IFERROR(I126/H126,0) -> 0 | K126: =H126-I126 -> 1
... A155: QC-001 | B155: ECD17011_NUEVOLABORATORIO GRB | C155: Electrica | D155: TABLERO REGULADOR FUTURO PARA SISTEMA FOTOVOLTAICO | E155: Instalacion | F155: TD-REG | G155: Registro De Instalacion | H155: 1 | I155: 0 | J155: =IFERROR(I155/H155,0) -> 0 | K155: =H155-I155 -> 1
A156: QC-001 | B156: ECD17011_NUEVOLABORATORIO GRB | C156: Electrica | D156: PANEL SOLAR MONOCRISTALINO | E156: Instalacion | G156: Registro De Instalacion | H156: 1 | I156: 0 | J156: =IFERROR(I156/H156,0) -> 0 | K156: =H156-I156 -> 1
A157: QC-001 | B157: ECD17011_NUEVOLABORATORIO GRB | C157: Electrica | D157: BANCO DE BATERÍAS SISTEMA FOTOVOLTÁICO | E157: Instalacion | F157: BAT-239-3 | G157: Registro De Instalacion | H157: 1 | I157: 0 | J157: =IFERROR(I157/H157,0) -> 0 | K157: =H157-I157 -> 1
A158: QC-002 | B158: ECD17011_NUEVOLABORATORIO GRB | C158: Electrica | D158: Transformador Servicios Generales red A | E158: Prueba de aislamiento | F158: B-TRA-239A | G158: Prueba | H158: 1 | I158: 0 | J158: =IFERROR(I158/H158,0) -> 0 | K158: =H158-I158 -> 1
A159: QC-002 | B159: ECD17011_NUEVOLABORATORIO GRB | C159: Electrica | D159: Transformador Servicios Generales red B | E159: Prueba de aislamiento | F159: B-TRA-239B | G159: Prueba | H159: 1 | I159: 0 | J159: =IFERROR(I159/H159,0) -> 0 | K159: =H159-I159 -> 1
A160: QC-002 | B160: ECD17011_NUEVOLABORATORIO GRB | C160: Electrica | D160: Unidad Chiller | E160: Prueba de aislamiento | F160: B-ENF-01 | G160: Prueba | H160: 1 | I160: 0 | J160: =IFERROR(I160/H160,0) -> 0 | K160: =H160-I160 -> 1
A161: QC-002 | B161: ECD17011_NUEVOLABORATORIO GRB | C161: Electrica | D161: Unidad Chiller | E161: Prueba de aislamiento | F161: B-ENF-02 | G161: Prueba | H161: 1 | I161: 0 | J161: =IFERROR(I161/H161,0) -> 0 | K161: =H161-I161 -> 1
A162: QC-002 | B162: ECD17011_NUEVOLABORATORIO GRB | C162: Electrica | D162: Torre de Enfriamiento | E162: Prueba de aislamiento | F162: B-TE-01 | G162: Prueba | H162: 1 | I162: 0 | J162: =IFERROR(I162/H162,0) -> 0 | K162: =H162-I162 -> 1
A163: QC-002 | B163: ECD17011_NUEVOLABORATORIO GRB | C163: Electrica | D163: Bomba de Condensación | E163: Prueba de aislamiento | F163: B-CDWP-03 | G163: Prueba | H163: 1 | I163: 0 | J163: =IFERROR(I163/H163,0) -> 0 | K163: =H163-I163 -> 1
A164: QC-002 | B164: ECD17011_NUEVOLABORATORIO GRB | C164: Electrica | D164: Bomba de Agua Fría | E164: Prueba de aislamiento | F164: B-CWP-01 | G164: Prueba | H164: 1 | I164: 0 | J164: =IFERROR(I164/H164,0) -> 0 | K164: =H164-I164 -> 1
A165: QC-002 | B165: ECD17011_NUEVOLABORATORIO GRB | C165: Electrica | D165: Bomba de Agua Fría | E165: Prueba de aislamiento | F165: B-CWP-02 | G165: Prueba | H165: 1 | I165: 0 | J165: =IFERROR(I165/H165,0) -> 0 | K165: =H165-I165 -> 1
A166: QC-002 | B166: ECD17011_NUEVOLABORATORIO GRB | C166: Electrica | D166: Unidad Extractora de aire | E166: Prueba de aislamiento | F166: B-UEX-01C | G166: Prueba | H166: 1 | I166: 0 | J166: =IFERROR(I166/H166,0) -> 0 | K166: =H166-I166 -> 1
A167: QC-002 | B167: ECD17011_NUEVOLABORATORIO GRB | C167: Electrica | D167: Unidad Extractora de aire | E167: Prueba de aislamiento | F167: B-UEX-01C' | G167: Prueba | H167: 1 | I167: 0 | J167: =IFERROR(I167/H167,0) -> 0 | K167: =H167-I167 -> 1
A168: QC-002 | B168: ECD17011_NUEVOLABORATORIO GRB | C168: Electrica | D168: Unidad Extractora de aire | E168: Prueba de aislamiento | F168: B-UEX-02A | G168: Prueba | H168: 1 | I168: 0 | J168: =IFERROR(I168/H168,0) -> 0 | K168: =H168-I168 -> 1
... A655: QC-002 | B655: ECD17011_NUEVOLABORATORIO GRB | C655: Electrica | D655: Sistema de Voz y Datos Distribuido | E655: Prueba de aislamiento | F655: B-TCC-239-2-C6 | G655: Prueba | H655: 1 | I655: 0 | J655: =IFERROR(I655/H655,0) -> 0 | K655: =H655-I655 -> 1

Sheet AVANCE
A1: 📊 AVANCE POR ACTIVIDAD — Conectado a MASTER_ACTIVIDADES & QC_DETALLE | Yesid Cruz
A2: ID | B2: PROYECTO | C2: TIPO | D2: CANTIDAD TOTAL (MASTER) | E2: EJECUTADO TOTAL (QC) | F2: % AVANCE | G2: PESO (%) | H2: AVANCE PONDERADO | I2: PENDIENTE | J2: ESTADO
A3: QA-001 | B3: ECD22005_SISTEMA B-2880 AZUFRE II ETAPA 2 | C3: QA | D3: {=IFERROR(IF(C3="QC",SUMPRODUCT((LEFT(QC_DETALLE!A$3:A$1000,LEN(A3))=A3)*(QC_DETALLE!B$3:B$1000=B3)*QC_DETALLE!H$3:H$1000),SUMPRODUCT((MASTER_ACTIVIDADES!A$3:A$198=A3)*(MASTER_ACTIVIDADES!F$3:F$198=B3)*(UPPER(MASTER_ACTIVIDADES!M$3:M$198)="SI")*MASTER_ACTIVIDADES!I$3:I$198)),0)} -> 1 | E3: {=IFERROR(IF(OR(C3="QC",C3="QA"), SUMPRODUCT((LEFT(QC_DETALLE!A$3:A$223,LEN(A3))=A3)*(QC_DETALLE!B$3:B$223=B3)*QC_DETALLE!I$3:I$223), SUMPRODUCT((MASTER_ACTIVIDADES!A$3:A$198=A3)*(MASTER_ACTIVIDADES!F$3:F$198=B3)*(UPPER(MASTER_ACTIVIDADES!M$3:M$198)="SI")*(MASTER_ACTIVIDADES!N$3:N$198="Completo")*MASTER_ACTIVIDADES!I$3:I$198)), 0)} -> 1 | F3: =IFERROR(E3/D3,0) -> 1 | G3: =IFERROR(IF(C3="QC",SUMPRODUCT((MASTER_ACTIVIDADES!A$3:A$198=A3)*(MASTER_ACTIVIDADES!F$3:F$198=B3)*(UPPER(MASTER_ACTIVIDADES!M$3:M$198)="SI")*MASTER_ACTIVIDADES!H$3:H$198)/IFERROR(COUNTIFS(MASTER_ACTIVIDADES!A$3:A$198,A3,MASTER_ACTIVIDADES!F$3:F$198,B3,MASTER_ACTIVIDADES!M$3:M$198,"SI"),1),SUMPRODUCT((MASTER_ACTIVIDADES!A$3:A$198=A3)*(MASTER_ACTIVIDADES!F$3:F$198=B3)*(UPPER(MASTER_ACTIVIDADES!M$3:M$198)="SI")*MASTER_ACTIVIDADES!H$3:H$198)/IFERROR(COUNTIFS(MASTER_ACTIVIDADES!A$3:A$198,A3,MASTER_ACTIVIDADES!F$3:F$198,B3,MASTER_ACTIVIDADES!M$3:M$198,"SI"),1)),0) -> 6 | H3: =IFERROR(F3*G3,0) -> 6 | I3: =IFERROR(D3-E3,0) -> 0 | J3: =IF(F3>=1,"✅ Completo",IF(F3>=0.7,"⚠️ En proceso","🔴 Pendiente")) -> ✅ Completo
A4: QA-002 | B4: ECD22005_SISTEMA B-2880 AZUFRE II ETAPA 2 | C4: QA | D4: {=IFERROR(IF(C4="QC",SUMPRODUCT((LEFT(QC_DETALLE!A$3:A$1000,LEN(A4))=A4)*(QC_DETALLE!B$3:B$1000=B4)*QC_DETALLE!H$3:H$1000),SUMPRODUCT((MASTER_ACTIVIDADES!A$3:A$198=A4)*(MASTER_ACTIVIDADES!F$3:F$198=B4)*(UPPER(MASTER_ACTIVIDADES!M$3:M$198)="SI")*MASTER_ACTIVIDADES!I$3:I$198)),0)} -> 1 | E4: {=IFERROR(IF(OR(C4="QC",C4="QA"), SUMPRODUCT((LEFT(QC_DETALLE!A$3:A$223,LEN(A4))=A4)*(QC_DETALLE!B$3:B$223=B4)*QC_DETALLE!I$3:I$223), SUMPRODUCT((MASTER_ACTIVIDADES!A$3:A$198=A4)*(MASTER_ACTIVIDADES!F$3:F$198=B4)*(UPPER(MASTER_ACTIVIDADES!M$3:M$198)="SI")*(MASTER_ACTIVIDADES!N$3:N$198="Completo")*MASTER_ACTIVIDADES!I$3:I$198)), 0)} -> 1 | F4: =IFERROR(E4/D4,0) -> 1 | G4: =IFERROR(IF(C4="QC",SUMPRODUCT((MASTER_ACTIVIDADES!A$3:A$198=A4)*(MASTER_ACTIVIDADES!F$3:F$198=B4)*(UPPER(MASTER_ACTIVIDADES!M$3:M$198)="SI")*MASTER_ACTIVIDADES!H$3:H$198)/IFERROR(COUNTIFS(MASTER_ACTIVIDADES!A$3:A$198,A4,MASTER_ACTIVIDADES!F$3:F$198,B4,MASTER_ACTIVIDADES!M$3:M$198,"SI"),1),SUMPRODUCT((MASTER_ACTIVIDADES!A$3:A$198=A4)*(MASTER_ACTIVIDADES!F$3:F$198=B4)*(UPPER(MASTER_ACTIVIDADES!M$3:M$198)="SI")*MASTER_ACTIVIDADES!H$3:H$198)/IFERROR(COUNTIFS(MASTER_ACTIVIDADES!A$3:A$198,A4,MASTER_ACTIVIDADES!F$3:F$198,B4,MASTER_ACTIVIDADES!M$3:M$198,"SI"),1)),0) -> 8 | H4: =IFERROR(F4*G4,0) -> 8 | I4: =IFERROR(D4-E4,0) -> 0 | J4: =IF(F4>=1,"✅ Completo",IF(F4>=0.7,"⚠️ En proceso","🔴 Pendiente")) -> ✅ Completo
A5: QA-003 | B5: ECD22005_SISTEMA B-2880 AZUFRE II ETAPA 2 | C5: QA | D5: {=IFERROR(IF(C5="QC",SUMPRODUCT((LEFT(QC_DETALLE!A$3:A$1000,LEN(A5))=A5)*(QC_DETALLE!B$3:B$1000=B5)*QC_DETALLE!H$3:H$1000),SUMPRODUCT((MASTER_ACTIVIDADES!A$3:A$198=A5)*(MASTER_ACTIVIDADES!F$3:F$198=B5)*(UPPER(MASTER_ACTIVIDADES!M$3:M$198)="SI")*MASTER_ACTIVIDADES!I$3:I$198)),0)} -> 1 | E5: {=IFERROR(IF(OR(C5="QC",C5="QA"), SUMPRODUCT((LEFT(QC_DETALLE!A$3:A$223,LEN(A5))=A5)*(QC_DETALLE!B$3:B$223=B5)*QC_DETALLE!I$3:I$223), SUMPRODUCT((MASTER_ACTIVIDADES!A$3:A$198=A5)*(MASTER_ACTIVIDADES!F$3:F$198=B5)*(UPPER(MASTER_ACTIVIDADES!M$3:M$198)="SI")*(MASTER_ACTIVIDADES!N$3:N$198="Completo")*MASTER_ACTIVIDADES!I$3:I$198)), 0)} -> 1 | F5: =IFERROR(E5/D5,0) -> 1 | G5: =IFERROR(IF(C5="QC",SUMPRODUCT((MASTER_ACTIVIDADES!A$3:A$198=A5)*(MASTER_ACTIVIDADES!F$3:F$198=B5)*(UPPER(MASTER_ACTIVIDADES!M$3:M$198)="SI")*MASTER_ACTIVIDADES!H$3:H$198)/IFERROR(COUNTIFS(MASTER_ACTIVIDADES!A$3:A$198,A5,MASTER_ACTIVIDADES!F$3:F$198,B5,MASTER_ACTIVIDADES!M$3:M$198,"SI"),1),SUMPRODUCT((MASTER_ACTIVIDADES!A$3:A$198=A5)*(MASTER_ACTIVIDADES!F$3:F$198=B5)*(UPPER(MASTER_ACTIVIDADES!M$3:M$198)="SI")*MASTER_ACTIVIDADES!H$3:H$198)/IFERROR(COUNTIFS(MASTER_ACTIVIDADES!A$3:A$198,A5,MASTER_ACTIVIDADES!F$3:F$198,B5,MASTER_ACTIVIDADES!M$3:M$198,"SI"),1)),0) -> 10 | H5: =IFERROR(F5*G5,0) -> 10 | I5: =IFERROR(D5-E5,0) -> 0 | J5: =IF(F5>=1,"✅ Completo",IF(F5>=0.7,"⚠️ En proceso","🔴 Pendiente")) -> ✅ Completo
A6: QC-001 | B6: ECD22005_SISTEMA B-2880 AZUFRE II ETAPA 2 | C6: QC | D6: {=IFERROR(IF(C6="QC",SUMPRODUCT((LEFT(QC_DETALLE!A$3:A$1000,LEN(A6))=A6)*(QC_DETALLE!B$3:B$1000=B6)*QC_DETALLE!H$3:H$1000),SUMPRODUCT((MASTER_ACTIVIDADES!A$3:A$198=A6)*(MASTER_ACTIVIDADES!F$3:F$198=B6)*(UPPER(MASTER_ACTIVIDADES!M$3:M$198)="SI")*MASTER_ACTIVIDADES!I$3:I$198)),0)} -> 2 | E6: {=IFERROR(IF(OR(C6="QC",C6="QA"), SUMPRODUCT((LEFT(QC_DETALLE!A$3:A$223,LEN(A6))=A6)*(QC_DETALLE!B$3:B$223=B6)*QC_DETALLE!I$3:I$223), SUMPRODUCT((MASTER_ACTIVIDADES!A$3:A$198=A6)*(MASTER_ACTIVIDADES!F$3:F$198=B6)*(UPPER(MASTER_ACTIVIDADES!M$3:M$198)="SI")*(MASTER_ACTIVIDADES!N$3:N$198="Completo")*MASTER_ACTIVIDADES!I$3:I$198)), 0)} -> 2 | F6: =IFERROR(E6/D6,0) -> 1 | G6: =IFERROR(IF(C6="QC",SUMPRODUCT((MASTER_ACTIVIDADES!A$3:A$198=A6)*(MASTER_ACTIVIDADES!F$3:F$198=B6)*(UPPER(MASTER_ACTIVIDADES!M$3:M$198)="SI")*MASTER_ACTIVIDADES!H$3:H$198)/IFERROR(COUNTIFS(MASTER_ACTIVIDADES!A$3:A$198,A6,MASTER_ACTIVIDADES!F$3:F$198,B6,MASTER_ACTIVIDADES!M$3:M$198,"SI"),1),SUMPRODUCT((MASTER_ACTIVIDADES!A$3:A$198=A6)*(MASTER_ACTIVIDADES!F$3:F$198=B6)*(UPPER(MASTER_ACTIVIDADES!M$3:M$198)="SI")*MASTER_ACTIVIDADES!H$3:H$198)/IFERROR(COUNTIFS(MASTER_ACTIVIDADES!A$3:A$198,A6,MASTER_ACTIVIDADES!F$3:F$198,B6,MASTER_ACTIVIDADES!M$3:M$198,"SI"),1)),0) -> 10 | H6: =IFERROR(F6*G6,0) -> 10 | I6: =IFERROR(D6-E6,0) -> 0 | J6: =IF(F6>=1,"✅ Completo",IF(F6>=0.7,"⚠️ En proceso","🔴 Pendiente")) -> ✅ Completo
A7: QC-002 | B7: ECD22005_SISTEMA B-2880 AZUFRE II ETAPA 2 | C7: QC | D7: {=IFERROR(IF(C7="QC",SUMPRODUCT((LEFT(QC_DETALLE!A$3:A$1000,LEN(A7))=A7)*(QC_DETALLE!B$3:B$1000=B7)*QC_DETALLE!H$3:H$1000),SUMPRODUCT((MASTER_ACTIVIDADES!A$3:A$198=A7)*(MASTER_ACTIVIDADES!F$3:F$198=B7)*(UPPER(MASTER_ACTIVIDADES!M$3:M$198)="SI")*MASTER_ACTIVIDADES!I$3:I$198)),0)} -> 28 | E7: {=IFERROR(IF(OR(C7="QC",C7="QA"), SUMPRODUCT((LEFT(QC_DETALLE!A$3:A$223,LEN(A7))=A7)*(QC_DETALLE!B$3:B$223=B7)*QC_DETALLE!I$3:I$223), SUMPRODUCT((MASTER_ACTIVIDADES!A$3:A$198=A7)*(MASTER_ACTIVIDADES!F$3:F$198=B7)*(UPPER(MASTER_ACTIVIDADES!M$3:M$198)="SI")*(MASTER_ACTIVIDADES!N$3:N$198="Completo")*MASTER_ACTIVIDADES!I$3:I$198)), 0)} -> 28 | F7: =IFERROR(E7/D7,0) -> 1 | G7: =IFERROR(IF(C7="QC",SUMPRODUCT((MASTER_ACTIVIDADES!A$3:A$198=A7)*(MASTER_ACTIVIDADES!F$3:F$198=B7)*(UPPER(MASTER_ACTIVIDADES!M$3:M$198)="SI")*MASTER_ACTIVIDADES!H$3:H$198)/IFERROR(COUNTIFS(MASTER_ACTIVIDADES!A$3:A$198,A7,MASTER_ACTIVIDADES!F$3:F$198,B7,MASTER_ACTIVIDADES!M$3:M$198,"SI"),1),SUMPRODUCT((MASTER_ACTIVIDADES!A$3:A$198=A7)*(MASTER_ACTIVIDADES!F$3:F$198=B7)*(UPPER(MASTER_ACTIVIDADES!M$3:M$198)="SI")*MASTER_ACTIVIDADES!H$3:H$198)/IFERROR(COUNTIFS(MASTER_ACTIVIDADES!A$3:A$198,A7,MASTER_ACTIVIDADES!F$3:F$198,B7,MASTER_ACTIVIDADES!M$3:M$198,"SI"),1)),0) -> 10 | H7: =IFERROR(F7*G7,0) -> 10 | I7: =IFERROR(D7-E7,0) -> 0 | J7: =IF(F7>=1,"✅ Completo",IF(F7>=0.7,"⚠️ En proceso","🔴 Pendiente")) -> ✅ Completo
A8: QC-003 | B8: ECD22005_SISTEMA B-2880 AZUFRE II ETAPA 2 | C8: QC | D8: {=IFERROR(IF(C8="QC",SUMPRODUCT((LEFT(QC_DETALLE!A$3:A$1000,LEN(A8))=A8)*(QC_DETALLE!B$3:B$1000=B8)*QC_DETALLE!H$3:H$1000),SUMPRODUCT((MASTER_ACTIVIDADES!A$3:A$198=A8)*(MASTER_ACTIVIDADES!F$3:F$198=B8)*(UPPER(MASTER_ACTIVIDADES!M$3:M$198)="SI")*MASTER_ACTIVIDADES!I$3:I$198)),0)} -> 2 | E8: {=IFERROR(IF(OR(C8="QC",C8="QA"), SUMPRODUCT((LEFT(QC_DETALLE!A$3:A$223,LEN(A8))=A8)*(QC_DETALLE!B$3:B$223=B8)*QC_DETALLE!I$3:I$223), SUMPRODUCT((MASTER_ACTIVIDADES!A$3:A$198=A8)*(MASTER_ACTIVIDADES!F$3:F$198=B8)*(UPPER(MASTER_ACTIVIDADES!M$3:M$198)="SI")*(MASTER_ACTIVIDADES!N$3:N$198="Completo")*MASTER_ACTIVIDADES!I$3:I$198)), 0)} -> 2 | F8: =IFERROR(E8/D8,0) -> 1 | G8: =IFERROR(IF(C8="QC",SUMPRODUCT((MASTER_ACTIVIDADES!A$3:A$198=A8)*(MASTER_ACTIVIDADES!F$3:F$198=B8)*(UPPER(MASTER_ACTIVIDADES!M$3:M$198)="SI")*MASTER_ACTIVIDADES!H$3:H$198)/IFERROR(COUNTIFS(MASTER_ACTIVIDADES!A$3:A$198,A8,MASTER_ACTIVIDADES!F$3:F$198,B8,MASTER_ACTIVIDADES!M$3:M$198,"SI"),1),SUMPRODUCT((MASTER_ACTIVIDADES!A$3:A$198=A8)*(MASTER_ACTIVIDADES!F$3:F$198=B8)*(UPPER(MASTER_ACTIVIDADES!M$3:M$198)="SI")*MASTER_ACTIVIDADES!H$3:H$198)/IFERROR(COUNTIFS(MASTER_ACTIVIDADES!A$3:A$198,A8,MASTER_ACTIVIDADES!F$3:F$198,B8,MASTER_ACTIVIDADES!M$3:M$198,"SI"),1)),0) -> 12 | H8: =IFERROR(F8*G8,0) -> 12 | I8: =IFERROR(D8-E8,0) -> 0 | J8: =IF(F8>=1,"✅ Completo",IF(F8>=0.7,"⚠️ En proceso","🔴 Pendiente")) -> ✅ Completo
A9: QC-004 | B9: ECD22005_SISTEMA B-2880 AZUFRE II ETAPA 2 | C9: QC | D9: {=IFERROR(IF(C9="QC",SUMPRODUCT((LEFT(QC_DETALLE!A$3:A$1000,LEN(A9))=A9)*(QC_DETALLE!B$3:B$1000=B9)*QC_DETALLE!H$3:H$1000),SUMPRODUCT((MASTER_ACTIVIDADES!A$3:A$198=A9)*(MASTER_ACTIVIDADES!F$3:F$198=B9)*(UPPER(MASTER_ACTIVIDADES!M$3:M$198)="SI")*MASTER_ACTIVIDADES!I$3:I$198)),0)} -> 2 | E9: {=IFERROR(IF(OR(C9="QC",C9="QA"), SUMPRODUCT((LEFT(QC_DETALLE!A$3:A$223,LEN(A9))=A9)*(QC_DETALLE!B$3:B$223=B9)*QC_DETALLE!I$3:I$223), SUMPRODUCT((MASTER_ACTIVIDADES!A$3:A$198=A9)*(MASTER_ACTIVIDADES!F$3:F$198=B9)*(UPPER(MASTER_ACTIVIDADES!M$3:M$198)="SI")*(MASTER_ACTIVIDADES!N$3:N$198="Completo")*MASTER_ACTIVIDADES!I$3:I$198)), 0)} -> 2 | F9: =IFERROR(E9/D9,0) -> 1 | G9: =IFERROR(IF(C9="QC",SUMPRODUCT((MASTER_ACTIVIDADES!A$3:A$198=A9)*(MASTER_ACTIVIDADES!F$3:F$198=B9)*(UPPER(MASTER_ACTIVIDADES!M$3:M$198)="SI")*MASTER_ACTIVIDADES!H$3:H$198)/IFERROR(COUNTIFS(MASTER_ACTIVIDADES!A$3:A$198,A9,MASTER_ACTIVIDADES!F$3:F$198,B9,MASTER_ACTIVIDADES!M$3:M$198,"SI"),1),SUMPRODUCT((MASTER_ACTIVIDADES!A$3:A$198=A9)*(MASTER_ACTIVIDADES!F$3:F$198=B9)*(UPPER(MASTER_ACTIVIDADES!M$3:M$198)="SI")*MASTER_ACTIVIDADES!H$3:H$198)/IFERROR(COUNTIFS(MASTER_ACTIVIDADES!A$3:A$198,A9,MASTER_ACTIVIDADES!F$3:F$198,B9,MASTER_ACTIVIDADES!M$3:M$198,"SI"),1)),0) -> 12 | H9: =IFERROR(F9*G9,0) -> 12 | I9: =IFERROR(D9-E9,0) -> 0 | J9: =IF(F9>=1,"✅ Completo",IF(F9>=0.7,"⚠️ En proceso","🔴 Pendiente")) -> ✅ Completo
A10: QC-005 | B10: ECD22005_SISTEMA B-2880 AZUFRE II ETAPA 2 | C10: QC | D10: {=IFERROR(IF(C10="QC",SUMPRODUCT((LEFT(QC_DETALLE!A$3:A$1000,LEN(A10))=A10)*(QC_DETALLE!B$3:B$1000=B10)*QC_DETALLE!H$3:H$1000),SUMPRODUCT((MASTER_ACTIVIDADES!A$3:A$198=A10)*(MASTER_ACTIVIDADES!F$3:F$198=B10)*(UPPER(MASTER_ACTIVIDADES!M$3:M$198)="SI")*MASTER_ACTIVIDADES!I$3:I$198)),0)} -> 2 | E10: {=IFERROR(IF(OR(C10="QC",C10="QA"), SUMPRODUCT((LEFT(QC_DETALLE!A$3:A$223,LEN(A10))=A10)*(QC_DETALLE!B$3:B$223=B10)*QC_DETALLE!I$3:I$223), SUMPRODUCT((MASTER_ACTIVIDADES!A$3:A$198=A10)*(MASTER_ACTIVIDADES!F$3:F$198=B10)*(UPPER(MASTER_ACTIVIDADES!M$3:M$198)="SI")*(MASTER_ACTIVIDADES!N$3:N$198="Completo")*MASTER_ACTIVIDADES!I$3:I$198)), 0)} -> 2 | F10: =IFERROR(E10/D10,0) -> 1 | G10: =IFERROR(IF(C10="QC",SUMPRODUCT((MASTER_ACTIVIDADES!A$3:A$198=A10)*(MASTER_ACTIVIDADES!F$3:F$198=B10)*(UPPER(MASTER_ACTIVIDADES!M$3:M$198)="SI")*MASTER_ACTIVIDADES!H$3:H$198)/IFERROR(COUNTIFS(MASTER_ACTIVIDADES!A$3:A$198,A10,MASTER_ACTIVIDADES!F$3:F$198,B10,MASTER_ACTIVIDADES!M$3:M$198,"SI"),1),SUMPRODUCT((MASTER_ACTIVIDADES!A$3:A$198=A10)*(MASTER_ACTIVIDADES!F$3:F$198=B10)*(UPPER(MASTER_ACTIVIDADES!M$3:M$198)="SI")*MASTER_ACTIVIDADES!H$3:H$198)/IFERROR(COUNTIFS(MASTER_ACTIVIDADES!A$3:A$198,A10,MASTER_ACTIVIDADES!F$3:F$198,B10,MASTER_ACTIVIDADES!M$3:M$198,"SI"),1)),0) -> 12 | H10: =IFERROR(F10*G10,0) -> 12 | I10: =IFERROR(D10-E10,0) -> 0 | J10: =IF(F10>=1,"✅ Completo",IF(F10>=0.7,"⚠️ En proceso","🔴 Pendiente")) -> ✅ Completo
A11: QA-001 | B11: ECD20005_LINEA BASE CALIDAD DE COMBUSTIBLE 10 PPM | C11: QA | D11: {=IFERROR(IF(C11="QC",SUMPRODUCT((LEFT(QC_DETALLE!A$3:A$1000,LEN(A11))=A11)*(QC_DETALLE!B$3:B$1000=B11)*QC_DETALLE!H$3:H$1000),SUMPRODUCT((MASTER_ACTIVIDADES!A$3:A$198=A11)*(MASTER_ACTIVIDADES!F$3:F$198=B11)*(UPPER(MASTER_ACTIVIDADES!M$3:M$198)="SI")*MASTER_ACTIVIDADES!I$3:I$198)),0)} -> 1 | E11: {=IFERROR(IF(OR(C11="QC",C11="QA"), SUMPRODUCT((LEFT(QC_DETALLE!A$3:A$223,LEN(A11))=A11)*(QC_DETALLE!B$3:B$223=B11)*QC_DETALLE!I$3:I$223), SUMPRODUCT((MASTER_ACTIVIDADES!A$3:A$198=A11)*(MASTER_ACTIVIDADES!F$3:F$198=B11)*(UPPER(MASTER_ACTIVIDADES!M$3:M$198)="SI")*(MASTER_ACTIVIDADES!N$3:N$198="Completo")*MASTER_ACTIVIDADES!I$3:I$198)), 0)} -> 1 | F11: =IFERROR(E11/D11,0) -> 1 | G11: =IFERROR(IF(C11="QC",SUMPRODUCT((MASTER_ACTIVIDADES!A$3:A$198=A11)*(MASTER_ACTIVIDADES!F$3:F$198=B11)*(UPPER(MASTER_ACTIVIDADES!M$3:M$198)="SI")*MASTER_ACTIVIDADES!H$3:H$198)/IFERROR(COUNTIFS(MASTER_ACTIVIDADES!A$3:A$198,A11,MASTER_ACTIVIDADES!F$3:F$198,B11,MASTER_ACTIVIDADES!M$3:M$198,"SI"),1),SUMPRODUCT((MASTER_ACTIVIDADES!A$3:A$198=A11)*(MASTER_ACTIVIDADES!F$3:F$198=B11)*(UPPER(MASTER_ACTIVIDADES!M$3:M$198)="SI")*MASTER_ACTIVIDADES!H$3:H$198)/IFERROR(COUNTIFS(MASTER_ACTIVIDADES!A$3:A$198,A11,MASTER_ACTIVIDADES!F$3:F$198,B11,MASTER_ACTIVIDADES!M$3:M$198,"SI"),1)),0) -> 8 | H11: =IFERROR(F11*G11,0) -> 8 | I11: =IFERROR(D11-E11,0) -> 0 | J11: =IF(F11>=1,"✅ Completo",IF(F11>=0.7,"⚠️ En proceso","🔴 Pendiente")) -> ✅ Completo
A12: QA-002 | B12: ECD20005_LINEA BASE CALIDAD DE COMBUSTIBLE 10 PPM | C12: QA | D12: {=IFERROR(IF(C12="QC",SUMPRODUCT((LEFT(QC_DETALLE!A$3:A$1000,LEN(A12))=A12)*(QC_DETALLE!B$3:B$1000=B12)*QC_DETALLE!H$3:H$1000),SUMPRODUCT((MASTER_ACTIVIDADES!A$3:A$198=A12)*(MASTER_ACTIVIDADES!F$3:F$198=B12)*(UPPER(MASTER_ACTIVIDADES!M$3:M$198)="SI")*MASTER_ACTIVIDADES!I$3:I$198)),0)} -> 1 | E12: {=IFERROR(IF(OR(C12="QC",C12="QA"), SUMPRODUCT((LEFT(QC_DETALLE!A$3:A$223,LEN(A12))=A12)*(QC_DETALLE!B$3:B$223=B12)*QC_DETALLE!I$3:I$223), SUMPRODUCT((MASTER_ACTIVIDADES!A$3:A$198=A12)*(MASTER_ACTIVIDADES!F$3:F$198=B12)*(UPPER(MASTER_ACTIVIDADES!M$3:M$198)="SI")*(MASTER_ACTIVIDADES!N$3:N$198="Completo")*MASTER_ACTIVIDADES!I$3:I$198)), 0)} -> 1 | F12: =IFERROR(E12/D12,0) -> 1 | G12: =IFERROR(IF(C12="QC",SUMPRODUCT((MASTER_ACTIVIDADES!A$3:A$198=A12)*(MASTER_ACTIVIDADES!F$3:F$198=B12)*(UPPER(MASTER_ACTIVIDADES!M$3:M$198)="SI")*MASTER_ACTIVIDADES!H$3:H$198)/IFERROR(COUNTIFS(MASTER_ACTIVIDADES!A$3:A$198,A12,MASTER_ACTIVIDADES!F$3:F$198,B12,MASTER_ACTIVIDADES!M$3:M$198,"SI"),1),SUMPRODUCT((MASTER_ACTIVIDADES!A$3:A$198=A12)*(MASTER_ACTIVIDADES!F$3:F$198=B12)*(UPPER(MASTER_ACTIVIDADES!M$3:M$198)="SI")*MASTER_ACTIVIDADES!H$3:H$198)/IFERROR(COUNTIFS(MASTER_ACTIVIDADES!A$3:A$198,A12,MASTER_ACTIVIDADES!F$3:F$198,B12,MASTER_ACTIVIDADES!M$3:M$198,"SI"),1)),0) -> 8 | H12: =IFERROR(F12*G12,0) -> 8 | I12: =IFERROR(D12-E12,0) -> 0 | J12: =IF(F12>=1,"✅ Completo",IF(F12>=0.7,"⚠️ En proceso","🔴 Pendiente")) -> ✅ Completo
A13: QA-003 | B13: ECD20005_LINEA BASE CALIDAD DE COMBUSTIBLE 10 PPM | C13: QA | D13: {=IFERROR(IF(C13="QC",SUMPRODUCT((LEFT(QC_DETALLE!A$3:A$1000,LEN(A13))=A13)*(QC_DETALLE!B$3:B$1000=B13)*QC_DETALLE!H$3:H$1000),SUMPRODUCT((MASTER_ACTIVIDADES!A$3:A$198=A13)*(MASTER_ACTIVIDADES!F$3:F$198=B13)*(UPPER(MASTER_ACTIVIDADES!M$3:M$198)="SI")*MASTER_ACTIVIDADES!I$3:I$198)),0)} -> 1 | E13: {=IFERROR(IF(OR(C13="QC",C13="QA"), SUMPRODUCT((LEFT(QC_DETALLE!A$3:A$223,LEN(A13))=A13)*(QC_DETALLE!B$3:B$223=B13)*QC_DETALLE!I$3:I$223), SUMPRODUCT((MASTER_ACTIVIDADES!A$3:A$198=A13)*(MASTER_ACTIVIDADES!F$3:F$198=B13)*(UPPER(MASTER_ACTIVIDADES!M$3:M$198)="SI")*(MASTER_ACTIVIDADES!N$3:N$198="Completo")*MASTER_ACTIVIDADES!I$3:I$198)), 0)} -> 0 | F13: =IFERROR(E13/D13,0) -> 0 | G13: =IFERROR(IF(C13="QC",SUMPRODUCT((MASTER_ACTIVIDADES!A$3:A$198=A13)*(MASTER_ACTIVIDADES!F$3:F$198=B13)*(UPPER(MASTER_ACTIVIDADES!M$3:M$198)="SI")*MASTER_ACTIVIDADES!H$3:H$198)/IFERROR(COUNTIFS(MASTER_ACTIVIDADES!A$3:A$198,A13,MASTER_ACTIVIDADES!F$3:F$198,B13,MASTER_ACTIVIDADES!M$3:M$198,"SI"),1),SUMPRODUCT((MASTER_ACTIVIDADES!A$3:A$198=A13)*(MASTER_ACTIVIDADES!F$3:F$198=B13)*(UPPER(MASTER_ACTIVIDADES!M$3:M$198)="SI")*MASTER_ACTIVIDADES!H$3:H$198)/IFERROR(COUNTIFS(MASTER_ACTIVIDADES!A$3:A$198,A13,MASTER_ACTIVIDADES!F$3:F$198,B13,MASTER_ACTIVIDADES!M$3:M$198,"SI"),1)),0) -> 8 | H13: =IFERROR(F13*G13,0) -> 0 | I13: =IFERROR(D13-E13,0) -> 1 | J13: =IF(F13>=1,"✅ Completo",IF(F13>=0.7,"⚠️ En proceso","🔴 Pendiente")) -> 🔴 Pendiente
A14: QA-004 | B14: ECD20005_LINEA BASE CALIDAD DE COMBUSTIBLE 10 PPM | C14: QA | D14: {=IFERROR(IF(C14="QC",SUMPRODUCT((LEFT(QC_DETALLE!A$3:A$1000,LEN(A14))=A14)*(QC_DETALLE!B$3:B$1000=B14)*QC_DETALLE!H$3:H$1000),SUMPRODUCT((MASTER_ACTIVIDADES!A$3:A$198=A14)*(MASTER_ACTIVIDADES!F$3:F$198=B14)*(UPPER(MASTER_ACTIVIDADES!M$3:M$198)="SI")*MASTER_ACTIVIDADES!I$3:I$198)),0)} -> 1 | E14: {=IFERROR(IF(OR(C14="QC",C14="QA"), SUMPRODUCT((LEFT(QC_DETALLE!A$3:A$223,LEN(A14))=A14)*(QC_DETALLE!B$3:B$223=B14)*QC_DETALLE!I$3:I$223), SUMPRODUCT((MASTER_ACTIVIDADES!A$3:A$198=A14)*(MASTER_ACTIVIDADES!F$3:F$198=B14)*(UPPER(MASTER_ACTIVIDADES!M$3:M$198)="SI")*(MASTER_ACTIVIDADES!N$3:N$198="Completo")*MASTER_ACTIVIDADES!I$3:I$198)), 0)} -> 0 | F14: =IFERROR(E14/D14,0) -> 0 | G14: =IFERROR(IF(C14="QC",SUMPRODUCT((MASTER_ACTIVIDADES!A$3:A$198=A14)*(MASTER_ACTIVIDADES!F$3:F$198=B14)*(UPPER(MASTER_ACTIVIDADES!M$3:M$198)="SI")*MASTER_ACTIVIDADES!H$3:H$198)/IFERROR(COUNTIFS(MASTER_ACTIVIDADES!A$3:A$198,A14,MASTER_ACTIVIDADES!F$3:F$198,B14,MASTER_ACTIVIDADES!M$3:M$198,"SI"),1),SUMPRODUCT((MASTER_ACTIVIDADES!A$3:A$198=A14)*(MASTER_ACTIVIDADES!F$3:F$198=B14)*(UPPER(MASTER_ACTIVIDADES!M$3:M$198)="SI")*MASTER_ACTIVIDADES!H$3:H$198)/IFERROR(COUNTIFS(MASTER_ACTIVIDADES!A$3:A$198,A14,MASTER_ACTIVIDADES!F$3:F$198,B14,MASTER_ACTIVIDADES!M$3:M$198,"SI"),1)),0) -> 8 | H14: =IFERROR(F14*G14,0) -> 0 | I14: =IFERROR(D14-E14,0) -> 1 | J14: =IF(F14>=1,"✅ Completo",IF(F14>=0.7,"⚠️ En proceso","🔴 Pendiente")) -> 🔴 Pendiente
... A24: QC-002 | B24: ECD17011_NUEVOLABORATORIO GRB | C24: QC | D24: {=IFERROR(IF(C24="QC",SUMPRODUCT((LEFT(QC_DETALLE!A$3:A$1000,LEN(A24))=A24)*(QC_DETALLE!B$3:B$1000=B24)*QC_DETALLE!H$3:H$1000),SUMPRODUCT((MASTER_ACTIVIDADES!A$3:A$198=A24)*(MASTER_ACTIVIDADES!F$3:F$198=B24)*(UPPER(MASTER_ACTIVIDADES!M$3:M$198)="SI")*MASTER_ACTIVIDADES!I$3:I$198)),0)} -> 498 | E24: {=IFERROR(IF(OR(C24="QC",C24="QA"), SUMPRODUCT((LEFT(QC_DETALLE!A$3:A$223,LEN(A24))=A24)*(QC_DETALLE!B$3:B$223=B24)*QC_DETALLE!I$3:I$223), SUMPRODUCT((MASTER_ACTIVIDADES!A$3:A$198=A24)*(MASTER_ACTIVIDADES!F$3:F$198=B24)*(UPPER(MASTER_ACTIVIDADES!M$3:M$198)="SI")*(MASTER_ACTIVIDADES!N$3:N$198="Completo")*MASTER_ACTIVIDADES!I$3:I$198)), 0)} -> 0 | F24: =IFERROR(E24/D24,0) -> 0 | G24: =IFERROR(IF(C24="QC",SUMPRODUCT((MASTER_ACTIVIDADES!A$3:A$198=A24)*(MASTER_ACTIVIDADES!F$3:F$198=B24)*(UPPER(MASTER_ACTIVIDADES!M$3:M$198)="SI")*MASTER_ACTIVIDADES!H$3:H$198)/IFERROR(COUNTIFS(MASTER_ACTIVIDADES!A$3:A$198,A24,MASTER_ACTIVIDADES!F$3:F$198,B24,MASTER_ACTIVIDADES!M$3:M$198,"SI"),1),SUMPRODUCT((MASTER_ACTIVIDADES!A$3:A$198=A24)*(MASTER_ACTIVIDADES!F$3:F$198=B24)*(UPPER(MASTER_ACTIVIDADES!M$3:M$198)="SI")*MASTER_ACTIVIDADES!H$3:H$198)/IFERROR(COUNTIFS(MASTER_ACTIVIDADES!A$3:A$198,A24,MASTER_ACTIVIDADES!F$3:F$198,B24,MASTER_ACTIVIDADES!M$3:M$198,"SI"),1)),0) -> 0.03 | H24: =IFERROR(F24*G24,0) -> 0 | I24: =IFERROR(D24-E24,0) -> 498 | J24: =IF(F24>=1,"✅ Completo",IF(F24>=0.7,"⚠️ En proceso","🔴 Pendiente")) -> 🔴 Pendiente
D25: {=IFERROR(IF(C25="QC",SUMPRODUCT((LEFT(QC_DETALLE!A$3:A$1000,LEN(A25))=A25)*(QC_DETALLE!B$3:B$1000=B25)*QC_DETALLE!H$3:H$1000),SUMPRODUCT((MASTER_ACTIVIDADES!A$3:A$198=A25)*(MASTER_ACTIVIDADES!F$3:F$198=B25)*(UPPER(MASTER_ACTIVIDADES!M$3:M$198)="SI")*MASTER_ACTIVIDADES!I$3:I$198)),0)} -> 0 | E25: {=IFERROR(IF(OR(C25="QC",C25="QA"), SUMPRODUCT((LEFT(QC_DETALLE!A$3:A$223,LEN(A25))=A25)*(QC_DETALLE!B$3:B$223=B25)*QC_DETALLE!I$3:I$223), SUMPRODUCT((MASTER_ACTIVIDADES!A$3:A$198=A25)*(MASTER_ACTIVIDADES!F$3:F$198=B25)*(UPPER(MASTER_ACTIVIDADES!M$3:M$198)="SI")*(MASTER_ACTIVIDADES!N$3:N$198="Completo")*MASTER_ACTIVIDADES!I$3:I$198)), 0)} -> 0 | F25: =IFERROR(E25/D25,0) -> 0 | G25: =IFERROR(IF(C25="QC",SUMPRODUCT((MASTER_ACTIVIDADES!A$3:A$198=A25)*(MASTER_ACTIVIDADES!F$3:F$198=B25)*(UPPER(MASTER_ACTIVIDADES!M$3:M$198)="SI")*MASTER_ACTIVIDADES!H$3:H$198)/IFERROR(COUNTIFS(MASTER_ACTIVIDADES!A$3:A$198,A25,MASTER_ACTIVIDADES!F$3:F$198,B25,MASTER_ACTIVIDADES!M$3:M$198,"SI"),1),SUMPRODUCT((MASTER_ACTIVIDADES!A$3:A$198=A25)*(MASTER_ACTIVIDADES!F$3:F$198=B25)*(UPPER(MASTER_ACTIVIDADES!M$3:M$198)="SI")*MASTER_ACTIVIDADES!H$3:H$198)/IFERROR(COUNTIFS(MASTER_ACTIVIDADES!A$3:A$198,A25,MASTER_ACTIVIDADES!F$3:F$198,B25,MASTER_ACTIVIDADES!M$3:M$198,"SI"),1)),0) -> 0 | H25: =IFERROR(F25*G25,0) -> 0 | I25: =IFERROR(D25-E25,0) -> 0 | J25: =IF(F25>=1,"✅ Completo",IF(F25>=0.7,"⚠️ En proceso","🔴 Pendiente")) -> 🔴 Pendiente

Sheet PLAN_SEMANAL
A1: 📅 PLAN SEMANAL — Programado vs. Ejecutado | QA/QC PRO Dashboard — Yesid Cruz
A2: ID | B2: FECHA | C2: SEMANA | D2: PROYECTO | E2: CANT. PROGRAMADA | F2: CANT. EJECUTADA | G2: DESVIACION | H2: % CUMPLIM. | I2: ESTADO
A3: QC-001 | B3: 46184 | C3: ="S"&WEEKNUM(PLAN_SEMANAL[[#This Row],[FECHA]]) -> S24 | D3: ECD22005_SISTEMA B-2880 AZUFRE II ETAPA 2 | E3: 1 | F3: 1 | G3: =E3-F3 -> 0 | H3: =IFERROR(F3/E3,0) -> 1 | I3: =IF(H3>=1,"✅ Cumplido",IF(H3>=0.7,"⚠️ Parcial","🔴 Crítico")) -> ✅ Cumplido
A4: QA-003 | B4: 46178 | C4: ="S"&WEEKNUM(PLAN_SEMANAL[[#This Row],[FECHA]]) -> S23 | D4: ECD20005_LINEA BASE CALIDAD DE COMBUSTIBLE 10 PPM | E4: 1 | F4: 0 | G4: =E4-F4 -> 1 | H4: =IFERROR(F4/E4,0) -> 0 | I4: =IF(H4>=1,"✅ Cumplido",IF(H4>=0.7,"⚠️ Parcial","🔴 Crítico")) -> 🔴 Crítico
A5: QC-002 | B5: 46178 | C5: ="S"&WEEKNUM(PLAN_SEMANAL[[#This Row],[FECHA]]) -> S23 | D5: ECD20005_LINEA BASE CALIDAD DE COMBUSTIBLE 10 PPM | E5: 1 | F5: 0 | G5: =E5-F5 -> 1 | H5: =IFERROR(F5/E5,0) -> 0 | I5: =IF(H5>=1,"✅ Cumplido",IF(H5>=0.7,"⚠️ Parcial","🔴 Crítico")) -> 🔴 Crítico
A6: QA-004 | B6: 46181 | C6: ="S"&WEEKNUM(PLAN_SEMANAL[[#This Row],[FECHA]]) -> S24 | D6: ECD20005_LINEA BASE CALIDAD DE COMBUSTIBLE 10 PPM | E6: 1 | F6: 0 | G6: =E6-F6 -> 1 | H6: =IFERROR(F6/E6,0) -> 0 | I6: =IF(H6>=1,"✅ Cumplido",IF(H6>=0.7,"⚠️ Parcial","🔴 Crítico")) -> 🔴 Crítico
C7: ="S"&WEEKNUM(PLAN_SEMANAL[[#This Row],[FECHA]]) -> S0 | G7: =E7-F7 -> 0 | H7: =IFERROR(F7/E7,0) -> 0 | I7: =IF(H7>=1,"✅ Cumplido",IF(H7>=0.7,"⚠️ Parcial","🔴 Crítico")) -> 🔴 Crítico
C8: ="S"&WEEKNUM(PLAN_SEMANAL[[#This Row],[FECHA]]) -> S0 | G8: =E8-F8 -> 0 | H8: =IFERROR(F8/E8,0) -> 0 | I8: =IF(H8>=1,"✅ Cumplido",IF(H8>=0.7,"⚠️ Parcial","🔴 Crítico")) -> 🔴 Crítico
C9: ="S"&WEEKNUM(PLAN_SEMANAL[[#This Row],[FECHA]]) -> S0 | G9: =E9-F9 -> 0 | H9: =IFERROR(F9/E9,0) -> 0 | I9: =IF(H9>=1,"✅ Cumplido",IF(H9>=0.7,"⚠️ Parcial","🔴 Crítico")) -> 🔴 Crítico
C10: ="S"&WEEKNUM(PLAN_SEMANAL[[#This Row],[FECHA]]) -> S0 | G10: =E10-F10 -> 0 | H10: =IFERROR(F10/E10,0) -> 0 | I10: =IF(H10>=1,"✅ Cumplido",IF(H10>=0.7,"⚠️ Parcial","🔴 Crítico")) -> 🔴 Crítico
C11: ="S"&WEEKNUM(PLAN_SEMANAL[[#This Row],[FECHA]]) -> S0 | G11: =E11-F11 -> 0 | H11: =IFERROR(F11/E11,0) -> 0 | I11: =IF(H11>=1,"✅ Cumplido",IF(H11>=0.7,"⚠️ Parcial","🔴 Crítico")) -> 🔴 Crítico

Sheet CERTIFICADOS
A1: 📜 CONTROL DE CERTIFICADOS — Calibración & Conformidad de Materiales | Yesid Cruz
A2: ID | B2: PROYECTO | C2: TIPO CERTIFICADO | D2: EQUIPO/MATERIAL | E2: ESPECIALIDAD | F2: PROGRAMADO | G2: ENTREGADO | H2: % AVANCE | I2: PESO | J2: AVANCE PONDERADO | K2: ESTADO | L2: CONTRATISTA
A3: CERT-001-AZUFRE-CALIBRACION | B3: ECD22005_SISTEMA B-2880 AZUFRE II ETAPA 2 | C3: Cert. Calibración | D3: Transmisor TT-301 Presión | E3: Instrumentación | F3: 5 | G3: 5 | H3: =IFERROR(G3/F3,0) -> 1 | I3: 20 | J3: =IFERROR(H3*I3,0) -> 20 | K3: =IF(H3>=1,"✅ Entregado","⏳ Pendiente") -> ✅ Entregado | L3: FERMAR
A4: CERT-001-AZUFRE-CALIBRACION | B4: ECD22005_SISTEMA B-2880 AZUFRE II ETAPA 2 | C4: Cert. Calibración | D4: Transmisor TT-401 Temperatura | E4: Instrumentación | F4: 3 | G4: 3 | H4: =IFERROR(G4/F4,0) -> 1 | I4: 20 | J4: =IFERROR(H4*I4,0) -> 20 | K4: =IF(H4>=1,"✅ Entregado","⏳ Pendiente") -> ✅ Entregado | L4: FERMAR
A5: CERT-002-C-AZUFRE-MATERIALES | B5: ECD22005_SISTEMA B-2880 AZUFRE II ETAPA 2 | C5: Conformidad Materiales | D5: Cable 4x10 AWG — Rollo 100m | E5: Eléctrica | F5: 5 | G5: 5 | H5: =IFERROR(G5/F5,0) -> 1 | I5: 20 | J5: =IFERROR(H5*I5,0) -> 20 | K5: =IF(H5>=1,"✅ Entregado","⏳ Pendiente") -> ✅ Entregado | L5: FERMAR
A6: CERT-002-C-AZUFRE-MATERIALES | B6: ECD22005_SISTEMA B-2880 AZUFRE II ETAPA 2 | C6: Conformidad Materiales | D6: Bandeja Portacables 200x100 | E6: Eléctrica | F6: 5 | G6: 5 | H6: =IFERROR(G6/F6,0) -> 1 | I6: 20 | J6: =IFERROR(H6*I6,0) -> 20 | K6: =IF(H6>=1,"✅ Entregado","⏳ Pendiente") -> ✅ Entregado | L6: FERMAR
A7: CERT-001-AZUFRE-CALIBRACION | B7: ECD22005_SISTEMA B-2880 AZUFRE II ETAPA 2 | C7: Cert. Calibración | D7: Megóhmetro Fluke 1550C | E7: Eléctrica | F7: 1 | G7: 1 | H7: =IFERROR(G7/F7,0) -> 1 | I7: 20 | J7: =IFERROR(H7*I7,0) -> 20 | K7: =IF(H7>=1,"✅ Entregado","⏳ Pendiente") -> ✅ Entregado | L7: FERMAR
A8: CERT-001-NUEVOLAB-CALIBRACION | B8: ECD17011_NUEVOLABORATORIO GRB | C8: Cert. Calibración | D8: Telurometro | E8: Electricaa | F8: 1 | G8: 1 | H8: =IFERROR(G8/F8,0) -> 1 | I8: 25 | J8: =IFERROR(H8*I8,0) -> 25 | K8: =IF(H8>=1,"✅ Entregado","⏳ Pendiente") -> ✅ Entregado | L8: OBCIPOL
A9: CERT-001-NUEVOLAB-CALIBRACION | B9: ECD17011_NUEVOLABORATORIO GRB | C9: Cert. Calibración | D9: Megóhmetro | E9: Eléctrica | F9: 1 | G9: 0 | H9: =IFERROR(G9/F9,0) -> 0 | I9: 25 | J9: =IFERROR(H9*I9,0) -> 0 | K9: =IF(H9>=1,"✅ Entregado","⏳ Pendiente") -> ⏳ Pendiente | L9: OBCIPOL
A10: CERT-001-NUEVOLAB-CALIBRACION | B10: ECD17011_NUEVOLABORATORIO GRB | C10: Cert. Calibración | D10: Multimetro | E10: Eléctrica | F10: 1 | G10: 0 | H10: =IFERROR(G10/F10,0) -> 0 | I10: 25 | J10: =IFERROR(H10*I10,0) -> 0 | K10: =IF(H10>=1,"✅ Entregado","⏳ Pendiente") -> ⏳ Pendiente | L10: OBCIPOL
A11: CERT-002-C-NUEVOLAB-MATERIALES | B11: ECD17011_NUEVOLABORATORIO GRB | C11: Conformidad Materiales | D11: Bandejas Portacables | E11: Eléctrica | F11: 1 | G11: 0 | H11: =IFERROR(G11/F11,0) -> 0 | I11: 25 | J11: =IFERROR(H11*I11,0) -> 0 | K11: =IF(H11>=1,"✅ Entregado","⏳ Pendiente") -> ⏳ Pendiente | L11: OBCIPOL
A12: CERT-002-C-NUEVOLAB-MATERIALES | B12: ECD17011_NUEVOLABORATORIO GRB | C12: Conformidad Materiales | D12: Tuberia Conduit | E12: Eléctrica | F12: 1 | G12: 0 | H12: =IFERROR(G12/F12,0) -> 0 | I12: 25 | J12: =IFERROR(H12*I12,0) -> 0 | K12: =IF(H12>=1,"✅ Entregado","⏳ Pendiente") -> ⏳ Pendiente | L12: OBCIPOL
A13: CERT-002-C-NUEVOLAB-MATERIALES | B13: ECD17011_NUEVOLABORATORIO GRB | C13: Conformidad Materiales | D13: Cable SPT | E13: Eléctrica | F13: 1 | G13: 0 | H13: =IFERROR(G13/F13,0) -> 0 | I13: 25 | J13: =IFERROR(H13*I13,0) -> 0 | K13: =IF(H13>=1,"✅ Entregado","⏳ Pendiente") -> ⏳ Pendiente | L13: OBCIPOL
A14: CERT-001-LBCC-CALIBRACION | B14: ECD20005_LINEA BASE CALIDAD DE COMBUSTIBLE 10 PPM | C14: Cert. Calibración | D14: Telurometro | E14: Electrica | F14: 1 | G14: 0 | H14: =IFERROR(G14/F14,0) -> 0 | I14: 20 | J14: =IFERROR(H14*I14,0) -> 0 | K14: =IF(H14>=1,"✅ Entregado","⏳ Pendiente") -> ⏳ Pendiente
A15: CERT-001-LBCC-CALIBRACION | B15: ECD20005_LINEA BASE CALIDAD DE COMBUSTIBLE 10 PPM | C15: Cert. Calibración | D15: Megóhmetro | E15: Electrica | F15: 1 | G15: 0 | H15: =IFERROR(G15/F15,0) -> 0 | I15: 20 | J15: =IFERROR(H15*I15,0) -> 0 | K15: =IF(H15>=1,"✅ Entregado","⏳ Pendiente") -> ⏳ Pendiente
A16: CERT-002-LBCC-MATERIALES | B16: ECD20005_LINEA BASE CALIDAD DE COMBUSTIBLE 10 PPM | C16: Cert. Calibración | D16: Multimetro | E16: Eléctrica | F16: 1 | G16: 0 | H16: =IFERROR(G16/F16,0) -> 0 | I16: 20 | J16: =IFERROR(H16*I16,0) -> 0 | K16: =IF(H16>=1,"✅ Entregado","⏳ Pendiente") -> ⏳ Pendiente
A17: CERT-002-LBCC-MATERIALES | B17: ECD20005_LINEA BASE CALIDAD DE COMBUSTIBLE 10 PPM | C17: Conformidad Materiales | D17: Cable THW 1/0 AWG | E17: Eléctrica | F17: 4 | G17: 4 | H17: =IFERROR(G17/F17,0) -> 1 | I17: 20 | J17: =IFERROR(H17*I17,0) -> 20 | K17: =IF(H17>=1,"✅ Entregado","⏳ Pendiente") -> ✅ Entregado
A18: CERT-001-LBCC-CALIBRACION | B18: ECD20005_LINEA BASE CALIDAD DE COMBUSTIBLE 10 PPM | C18: Cert. Calibración | D18: Pinza Voltech AT3600 | E18: Instrumentación | F18: 1 | G18: 1 | H18: =IFERROR(G18/F18,0) -> 1 | I18: 20 | J18: =IFERROR(H18*I18,0) -> 20 | K18: =IF(H18>=1,"✅ Entregado","⏳ Pendiente") -> ✅ Entregado

Sheet CONSOLIDADO
A1: 📋 CONSOLIDADO POR PROYECTO — KPIs Globales | Responsable: Yesid Cruz
A2: PROYECTO CORTO | B2: PROYECTO LARGO | C2: TOTAL ITEMS (APLICA=SI) | D2: COMPLETOS | E2: PENDIENTES | F2: % AVANCE TOTAL | G2: % AVANCE QA | H2: % AVANCE QC | I2: ESTADO GENERAL
A3: =CALC_DATA!A3 -> AZUFRE II | B3: =CALC_DATA!B3 -> ECD22005_SISTEMA B-2880 AZUFRE II ETAPA 2 | C3: =CALC_DATA!C3 -> 8 | D3: =CALC_DATA!D3 -> 8 | E3: =CALC_DATA!E3 -> 0 | F3: =CALC_DATA!F3 -> 1 | G3: =CALC_DATA!G3 -> 1 | H3: =CALC_DATA!H3 -> 1 | I3: =IF(F3>=0.9,"✅ Verde",IF(F3>=0.7,"⚠️ Amarillo","🔴 Crítico")) -> ✅ Verde
A4: =CALC_DATA!A4 -> NUEVOLABORATORIO | B4: =CALC_DATA!B4 -> ECD17011_NUEVOLABORATORIO GRB | C4: =CALC_DATA!C4 -> 2 | D4: =CALC_DATA!D4 -> 0 | E4: =CALC_DATA!E4 -> 2 | F4: =CALC_DATA!F4 -> 0 | G4: =CALC_DATA!G4 -> 0 | H4: =CALC_DATA!H4 -> 0 | I4: =IF(F4>=0.9,"✅ Verde",IF(F4>=0.7,"⚠️ Amarillo","🔴 Crítico")) -> 🔴 Crítico
A5: =CALC_DATA!A5 -> LBCC 10PPM | B5: =CALC_DATA!B5 -> ECD20005_LINEA BASE CALIDAD DE COMBUSTIBLE 10 PPM | C5: =CALC_DATA!C5 -> 12 | D5: =CALC_DATA!D5 -> 2 | E5: =CALC_DATA!E5 -> 10 | F5: =CALC_DATA!F5 -> 0.19557416 | G5: =CALC_DATA!G5 -> 0.33333333 | H5: =CALC_DATA!H5 -> 0.030263158 | I5: =IF(F5>=0.9,"✅ Verde",IF(F5>=0.7,"⚠️ Amarillo","🔴 Crítico")) -> 🔴 Crítico
A6: =CALC_DATA!A6 -> PROYECTO 4 | B6: =CALC_DATA!B6 -> 0 | C6: =CALC_DATA!C6 -> 0 | D6: =CALC_DATA!D6 -> 0 | E6: =CALC_DATA!E6 -> 0 | F6: =CALC_DATA!F6 -> 0 | G6: =CALC_DATA!G6 -> 0 | H6: =CALC_DATA!H6 -> 0 | I6: =IF(F6>=0.9,"✅ Verde",IF(F6>=0.7,"⚠️ Amarillo","🔴 Crítico")) -> 🔴 Crítico
A7: =CALC_DATA!A7 -> PROYECTO 5 | B7: =CALC_DATA!B7 -> 0 | C7: =CALC_DATA!C7 -> 0 | D7: =CALC_DATA!D7 -> 0 | E7: =CALC_DATA!E7 -> 0 | F7: =CALC_DATA!F7 -> 0 | G7: =CALC_DATA!G7 -> 0 | H7: =CALC_DATA!H7 -> 0 | I7: =IF(F7>=0.9,"✅ Verde",IF(F7>=0.7,"⚠️ Amarillo","🔴 Crítico")) -> 🔴 Crítico
A8: =CALC_DATA!A8 -> PROYECTO 6 | B8: =CALC_DATA!B8 -> 0 | C8: =CALC_DATA!C8 -> 0 | D8: =CALC_DATA!D8 -> 0 | E8: =CALC_DATA!E8 -> 0 | F8: =CALC_DATA!F8 -> 0 | G8: =CALC_DATA!G8 -> 0 | H8: =CALC_DATA!H8 -> 0 | I8: =IF(F8>=0.9,"✅ Verde",IF(F8>=0.7,"⚠️ Amarillo","🔴 Crítico")) -> 🔴 Crítico
A9: =CALC_DATA!A9 -> PROYECTO 7 | B9: =CALC_DATA!B9 -> 0 | C9: =CALC_DATA!C9 -> 0 | D9: =CALC_DATA!D9 -> 0 | E9: =CALC_DATA!E9 -> 0 | F9: =CALC_DATA!F9 -> 0 | G9: =CALC_DATA!G9 -> 0 | H9: =CALC_DATA!H9 -> 0 | I9: =IF(F9>=0.9,"✅ Verde",IF(F9>=0.7,"⚠️ Amarillo","🔴 Crítico")) -> 🔴 Crítico
A10: =CALC_DATA!A10 -> PROYECTO 8 | B10: =CALC_DATA!B10 -> 0 | C10: =CALC_DATA!C10 -> 0 | D10: =CALC_DATA!D10 -> 0 | E10: =CALC_DATA!E10 -> 0 | F10: =CALC_DATA!F10 -> 0 | G10: =CALC_DATA!G10 -> 0 | H10: =CALC_DATA!H10 -> 0 | I10: =IF(F10>=0.9,"✅ Verde",IF(F10>=0.7,"⚠️ Amarillo","🔴 Crítico")) -> 🔴 Crítico
A11: =CALC_DATA!A11 -> PROYECTO 9 | B11: =CALC_DATA!B11 -> 0 | C11: =CALC_DATA!C11 -> 0 | D11: =CALC_DATA!D11 -> 0 | E11: =CALC_DATA!E11 -> 0 | F11: =CALC_DATA!F11 -> 0 | G11: =CALC_DATA!G11 -> 0 | H11: =CALC_DATA!H11 -> 0 | I11: =IF(F11>=0.9,"✅ Verde",IF(F11>=0.7,"⚠️ Amarillo","🔴 Crítico")) -> 🔴 Crítico
A12: =CALC_DATA!A12 -> PROYECTO 10 | B12: =CALC_DATA!B12 -> 0 | C12: =CALC_DATA!C12 -> 0 | D12: =CALC_DATA!D12 -> 0 | E12: =CALC_DATA!E12 -> 0 | F12: =CALC_DATA!F12 -> 0 | G12: =CALC_DATA!G12 -> 0 | H12: =CALC_DATA!H12 -> 0 | I12: =IF(F12>=0.9,"✅ Verde",IF(F12>=0.7,"⚠️ Amarillo","🔴 Crítico")) -> 🔴 Crítico
A13: TOTAL GLOBAL — Todos los proyectos | C13: =IFERROR(SUM(C3:C12),0) -> 22 | D13: =IFERROR(SUM(D3:D12),0) -> 10 | E13: =IFERROR(SUM(E3:E12),0) -> 12 | F13: =IFERROR(SUMPRODUCT((AVANCE!A$3:A$206<>"")*AVANCE!G$3:G$206*AVANCE!F$3:F$206)/IFERROR(SUMPRODUCT((AVANCE!A$3:A$206<>"")*AVANCE!G$3:G$206),1),0) -> 0.5784275 | G13: =IFERROR(SUMPRODUCT((AVANCE!C$3:C$206="QA")*AVANCE!G$3:G$206*AVANCE!F$3:F$206)/IFERROR(SUMPRODUCT((AVANCE!C$3:C$206="QA")*AVANCE!G$3:G$206),1),0) -> 0.55555556 | H13: =IFERROR(SUMPRODUCT((AVANCE!C$3:C$206="QC")*AVANCE!G$3:G$206*AVANCE!F$3:F$206)/IFERROR(SUMPRODUCT((AVANCE!C$3:C$206="QC")*AVANCE!G$3:G$206),1),0) -> 0.59557075 | I13: =IF(F13>=0.9,"✅ Verde",IF(F13>=0.7,"⚠️ Amarillo","🔴 Crítico")) -> 🔴 Crítico

Sheet REGISTRO_NC
A1: ⚠️ REGISTRO DE NO CONFORMIDADES (NC) | QA/QC PRO Dashboard — Yesid Cruz
A2: N° NC | B2: FECHA DETECCIÓN | C2: PROYECTO | D2: ESPECIALIDAD | E2: DESCRIPCIÓN | F2: CAUSA RAÍZ | G2: RESPONSABLE CIERRE | H2: FECHA LÍMITE | I2: ESTADO | J2: ACCION CORRECTIVA | K2: EVIDENCIA
A3: NCR-008 | B3: 20/05/2025 | C3: ECD17011_NUEVOLABORATORIO GRB | D3: Eléctrica | E3: Oxidación severa en perfiles soporte de bandejas portacables en área B-2880, tramo entre B-03 y B-07 | F3: No se puede evidenciar la calidad del los perfiles, el contratista no presenta certificado de calidad avalados por la ONAC | G3: Lenar Parra | H3: 06/06/2025 | I3: 🔴 Abierta | J3: Cambiar los perfiles y presentar certificacion de conformidad RETIE | K3: Fotos 1
A4: NCR-009 | B4: 20/05/2025 | C4: ECD17011_NUEVOLABORATORIO GRB | D4: Eléctrica | E4: Oxidación severa en perfiles soporte de bandejas portacables en área B-2880, tramo entre B-03 y B-07 | F4: No se puede evidenciar la calidad del los perfiles, el contratista no presenta certificado de calidad avalados por la ONAC | G4: Lineth Barroso | H4: 06/06/2025 | I4: 🔴 Abierta | J4: Cambiar los perfiles y presentar certificacion de conformidad RETIE | K4: Fotos 2

Sheet CALC_DATA
A1: ⚙️ CALC_DATA — Tabla auxiliar de KPIs (alimenta DASHBOARD_PRO) — NO EDITAR MANUALMENTE
A2: PROYECTO_CORTO | B2: PROYECTO_LARGO | C2: TOTAL_ITEMS | D2: COMPLETOS | E2: PENDIENTES | F2: PCT_AVANCE | G2: QA_PCT | H2: QC_PCT
A3: AZUFRE II | B3: ECD22005_SISTEMA B-2880 AZUFRE II ETAPA 2 | C3: =IFERROR(COUNTIF(AVANCE!B$3:B$206,B3),0) -> 8 | D3: =IFERROR(COUNTIFS(AVANCE!B$3:B$206,B3,AVANCE!J$3:J$206,"✅ Completo"),0) -> 8 | E3: =IFERROR(C3-D3,0) -> 0 | F3: =IFERROR(SUMPRODUCT((AVANCE!B$3:B$206=B3)*AVANCE!H$3:H$206)/IFERROR(SUMPRODUCT((AVANCE!B$3:B$206=B3)*AVANCE!G$3:G$206),1),0) -> 1 | G3: =IFERROR(SUMPRODUCT((AVANCE!B$3:B$206=B3)*(AVANCE!C$3:C$206="QA")*AVANCE!H$3:H$206)/IFERROR(SUMPRODUCT((AVANCE!B$3:B$206=B3)*(AVANCE!C$3:C$206="QA")*AVANCE!G$3:G$206),1),0) -> 1 | H3: =IFERROR(SUMPRODUCT((AVANCE!B$3:B$206=B3)*(AVANCE!C$3:C$206="QC")*AVANCE!H$3:H$206)/IFERROR(SUMPRODUCT((AVANCE!B$3:B$206=B3)*(AVANCE!C$3:C$206="QC")*AVANCE!G$3:G$206),1),0) -> 1
A4: NUEVOLABORATORIO | B4: ECD17011_NUEVOLABORATORIO GRB | C4: =IFERROR(COUNTIF(AVANCE!B$3:B$206,B4),0) -> 2 | D4: =IFERROR(COUNTIFS(AVANCE!B$3:B$206,B4,AVANCE!J$3:J$206,"✅ Completo"),0) -> 0 | E4: =IFERROR(C4-D4,0) -> 2 | F4: =IFERROR(SUMPRODUCT((AVANCE!B$3:B$206=B4)*AVANCE!H$3:H$206)/IFERROR(SUMPRODUCT((AVANCE!B$3:B$206=B4)*AVANCE!G$3:G$206),1),0) -> 0 | G4: =IFERROR(SUMPRODUCT((AVANCE!B$3:B$206=B4)*(AVANCE!C$3:C$206="QA")*AVANCE!H$3:H$206)/IFERROR(SUMPRODUCT((AVANCE!B$3:B$206=B4)*(AVANCE!C$3:C$206="QA")*AVANCE!G$3:G$206),1),0) -> 0 | H4: =IFERROR(SUMPRODUCT((AVANCE!B$3:B$206=B4)*(AVANCE!C$3:C$206="QC")*AVANCE!H$3:H$206)/IFERROR(SUMPRODUCT((AVANCE!B$3:B$206=B4)*(AVANCE!C$3:C$206="QC")*AVANCE!G$3:G$206),1),0) -> 0
A5: LBCC 10PPM | B5: ECD20005_LINEA BASE CALIDAD DE COMBUSTIBLE 10 PPM | C5: =IFERROR(COUNTIF(AVANCE!B$3:B$206,B5),0) -> 12 | D5: =IFERROR(COUNTIFS(AVANCE!B$3:B$206,B5,AVANCE!J$3:J$206,"✅ Completo"),0) -> 2 | E5: =IFERROR(C5-D5,0) -> 10 | F5: =IFERROR(SUMPRODUCT((AVANCE!B$3:B$206=B5)*AVANCE!H$3:H$206)/IFERROR(SUMPRODUCT((AVANCE!B$3:B$206=B5)*AVANCE!G$3:G$206),1),0) -> 0.19557416 | G5: =IFERROR(SUMPRODUCT((AVANCE!B$3:B$206=B5)*(AVANCE!C$3:C$206="QA")*AVANCE!H$3:H$206)/IFERROR(SUMPRODUCT((AVANCE!B$3:B$206=B5)*(AVANCE!C$3:C$206="QA")*AVANCE!G$3:G$206),1),0) -> 0.33333333 | H5: =IFERROR(SUMPRODUCT((AVANCE!B$3:B$206=B5)*(AVANCE!C$3:C$206="QC")*AVANCE!H$3:H$206)/IFERROR(SUMPRODUCT((AVANCE!B$3:B$206=B5)*(AVANCE!C$3:C$206="QC")*AVANCE!G$3:G$206),1),0) -> 0.030263158
A6: PROYECTO 4 | C6: =IFERROR(COUNTIF(AVANCE!B$3:B$207,B6),0) -> 0 | D6: =IFERROR(COUNTIFS(AVANCE!B$3:B$207,B6,AVANCE!F$3:F$207,1),0) -> 0 | E6: =IFERROR(C6-D6,0) -> 0 | F6: =IFERROR(SUMPRODUCT((AVANCE!B$3:B$207=B6)*AVANCE!H$3:H$207)/SUMPRODUCT((AVANCE!B$3:B$207=B6)*AVANCE!G$3:G$207),0) -> 0 | G6: =IFERROR(SUMPRODUCT((AVANCE!B$3:B$207=B6)*(AVANCE!C$3:C$207="QA")*AVANCE!H$3:H$207)/SUMPRODUCT((AVANCE!B$3:B$207=B6)*(AVANCE!C$3:C$207="QA")*AVANCE!G$3:G$207),0) -> 0 | H6: =IFERROR(SUMPRODUCT((AVANCE!B$3:B$207=B6)*(AVANCE!C$3:C$207="QC")*AVANCE!H$3:H$207)/SUMPRODUCT((AVANCE!B$3:B$207=B6)*(AVANCE!C$3:C$207="QC")*AVANCE!G$3:G$207),0) -> 0
A7: PROYECTO 5 | C7: =IFERROR(COUNTIF(AVANCE!B$3:B$207,B7),0) -> 0 | D7: =IFERROR(COUNTIFS(AVANCE!B$3:B$207,B7,AVANCE!F$3:F$207,1),0) -> 0 | E7: =IFERROR(C7-D7,0) -> 0 | F7: =IFERROR(SUMPRODUCT((AVANCE!B$3:B$207=B7)*AVANCE!H$3:H$207)/SUMPRODUCT((AVANCE!B$3:B$207=B7)*AVANCE!G$3:G$207),0) -> 0 | G7: =IFERROR(SUMPRODUCT((AVANCE!B$3:B$207=B7)*(AVANCE!C$3:C$207="QA")*AVANCE!H$3:H$207)/SUMPRODUCT((AVANCE!B$3:B$207=B7)*(AVANCE!C$3:C$207="QA")*AVANCE!G$3:G$207),0) -> 0 | H7: =IFERROR(SUMPRODUCT((AVANCE!B$3:B$207=B7)*(AVANCE!C$3:C$207="QC")*AVANCE!H$3:H$207)/SUMPRODUCT((AVANCE!B$3:B$207=B7)*(AVANCE!C$3:C$207="QC")*AVANCE!G$3:G$207),0) -> 0
A8: PROYECTO 6 | C8: =IFERROR(COUNTIF(AVANCE!B$3:B$207,B8),0) -> 0 | D8: =IFERROR(COUNTIFS(AVANCE!B$3:B$207,B8,AVANCE!F$3:F$207,1),0) -> 0 | E8: =IFERROR(C8-D8,0) -> 0 | F8: =IFERROR(SUMPRODUCT((AVANCE!B$3:B$207=B8)*AVANCE!H$3:H$207)/SUMPRODUCT((AVANCE!B$3:B$207=B8)*AVANCE!G$3:G$207),0) -> 0 | G8: =IFERROR(SUMPRODUCT((AVANCE!B$3:B$207=B8)*(AVANCE!C$3:C$207="QA")*AVANCE!H$3:H$207)/SUMPRODUCT((AVANCE!B$3:B$207=B8)*(AVANCE!C$3:C$207="QA")*AVANCE!G$3:G$207),0) -> 0 | H8: =IFERROR(SUMPRODUCT((AVANCE!B$3:B$207=B8)*(AVANCE!C$3:C$207="QC")*AVANCE!H$3:H$207)/SUMPRODUCT((AVANCE!B$3:B$207=B8)*(AVANCE!C$3:C$207="QC")*AVANCE!G$3:G$207),0) -> 0
A9: PROYECTO 7 | C9: =IFERROR(COUNTIF(AVANCE!B$3:B$207,B9),0) -> 0 | D9: =IFERROR(COUNTIFS(AVANCE!B$3:B$207,B9,AVANCE!F$3:F$207,1),0) -> 0 | E9: =IFERROR(C9-D9,0) -> 0 | F9: =IFERROR(SUMPRODUCT((AVANCE!B$3:B$207=B9)*AVANCE!H$3:H$207)/SUMPRODUCT((AVANCE!B$3:B$207=B9)*AVANCE!G$3:G$207),0) -> 0 | G9: =IFERROR(SUMPRODUCT((AVANCE!B$3:B$207=B9)*(AVANCE!C$3:C$207="QA")*AVANCE!H$3:H$207)/SUMPRODUCT((AVANCE!B$3:B$207=B9)*(AVANCE!C$3:C$207="QA")*AVANCE!G$3:G$207),0) -> 0 | H9: =IFERROR(SUMPRODUCT((AVANCE!B$3:B$207=B9)*(AVANCE!C$3:C$207="QC")*AVANCE!H$3:H$207)/SUMPRODUCT((AVANCE!B$3:B$207=B9)*(AVANCE!C$3:C$207="QC")*AVANCE!G$3:G$207),0) -> 0
A10: PROYECTO 8 | C10: =IFERROR(COUNTIF(AVANCE!B$3:B$207,B10),0) -> 0 | D10: =IFERROR(COUNTIFS(AVANCE!B$3:B$207,B10,AVANCE!F$3:F$207,1),0) -> 0 | E10: =IFERROR(C10-D10,0) -> 0 | F10: =IFERROR(SUMPRODUCT((AVANCE!B$3:B$207=B10)*AVANCE!H$3:H$207)/SUMPRODUCT((AVANCE!B$3:B$207=B10)*AVANCE!G$3:G$207),0) -> 0 | G10: =IFERROR(SUMPRODUCT((AVANCE!B$3:B$207=B10)*(AVANCE!C$3:C$207="QA")*AVANCE!H$3:H$207)/SUMPRODUCT((AVANCE!B$3:B$207=B10)*(AVANCE!C$3:C$207="QA")*AVANCE!G$3:G$207),0) -> 0 | H10: =IFERROR(SUMPRODUCT((AVANCE!B$3:B$207=B10)*(AVANCE!C$3:C$207="QC")*AVANCE!H$3:H$207)/SUMPRODUCT((AVANCE!B$3:B$207=B10)*(AVANCE!C$3:C$207="QC")*AVANCE!G$3:G$207),0) -> 0
A11: PROYECTO 9 | C11: =IFERROR(COUNTIF(AVANCE!B$3:B$207,B11),0) -> 0 | D11: =IFERROR(COUNTIFS(AVANCE!B$3:B$207,B11,AVANCE!F$3:F$207,1),0) -> 0 | E11: =IFERROR(C11-D11,0) -> 0 | F11: =IFERROR(SUMPRODUCT((AVANCE!B$3:B$207=B11)*AVANCE!H$3:H$207)/SUMPRODUCT((AVANCE!B$3:B$207=B11)*AVANCE!G$3:G$207),0) -> 0 | G11: =IFERROR(SUMPRODUCT((AVANCE!B$3:B$207=B11)*(AVANCE!C$3:C$207="QA")*AVANCE!H$3:H$207)/SUMPRODUCT((AVANCE!B$3:B$207=B11)*(AVANCE!C$3:C$207="QA")*AVANCE!G$3:G$207),0) -> 0 | H11: =IFERROR(SUMPRODUCT((AVANCE!B$3:B$207=B11)*(AVANCE!C$3:C$207="QC")*AVANCE!H$3:H$207)/SUMPRODUCT((AVANCE!B$3:B$207=B11)*(AVANCE!C$3:C$207="QC")*AVANCE!G$3:G$207),0) -> 0
A12: PROYECTO 10 | C12: =IFERROR(COUNTIF(AVANCE!B$3:B$207,B12),0) -> 0 | D12: =IFERROR(COUNTIFS(AVANCE!B$3:B$207,B12,AVANCE!F$3:F$207,1),0) -> 0 | E12: =IFERROR(C12-D12,0) -> 0 | F12: =IFERROR(SUMPRODUCT((AVANCE!B$3:B$207=B12)*AVANCE!H$3:H$207)/SUMPRODUCT((AVANCE!B$3:B$207=B12)*AVANCE!G$3:G$207),0) -> 0 | G12: =IFERROR(SUMPRODUCT((AVANCE!B$3:B$207=B12)*(AVANCE!C$3:C$207="QA")*AVANCE!H$3:H$207)/SUMPRODUCT((AVANCE!B$3:B$207=B12)*(AVANCE!C$3:C$207="QA")*AVANCE!G$3:G$207),0) -> 0 | H12: =IFERROR(SUMPRODUCT((AVANCE!B$3:B$207=B12)*(AVANCE!C$3:C$207="QC")*AVANCE!H$3:H$207)/SUMPRODUCT((AVANCE!B$3:B$207=B12)*(AVANCE!C$3:C$207="QC")*AVANCE!G$3:G$207),0) -> 0
A14: KPI | B14: VALOR | D14: SEMANA | E14: PROGRAMADO | F14: EJECUTADO | G14: CUMPLIMIENTO_%
A15: TOTAL_ACTIVIDADES | B15: =IFERROR(SUM(C3:C12),0) -> 22 | D15: =PLAN_SEMANAL!C3 -> S24 | E15: =IFERROR(SUMIF(PLAN_SEMANAL!C$3:C$200,"S21",PLAN_SEMANAL!E$3:E$200),0) -> 0 | F15: =IFERROR(SUMIF(PLAN_SEMANAL!C$3:C$200,"S21",PLAN_SEMANAL!F$3:F$200),0) -> 0 | G15: =IFERROR(F15/E15,0) -> 0
A16: COMPLETAS | B16: =IFERROR(SUM(D3:D12),0) -> 10 | D16: =PLAN_SEMANAL!C4 -> S23 | E16: =IFERROR(SUMIF(PLAN_SEMANAL!C$3:C$200,"S22",PLAN_SEMANAL!E$3:E$200),0) -> 0 | F16: =IFERROR(SUMIF(PLAN_SEMANAL!C$3:C$200,"S22",PLAN_SEMANAL!F$3:F$200),0) -> 0 | G16: =IFERROR(F16/E16,0) -> 0
A17: PENDIENTES | B17: =IFERROR(SUM(E3:E12),0) -> 12 | D17: =PLAN_SEMANAL!C5 -> S23 | E17: =IFERROR(SUMIF(PLAN_SEMANAL!C$3:C$200,"S23",PLAN_SEMANAL!E$3:E$200),0) -> 2 | F17: =IFERROR(SUMIF(PLAN_SEMANAL!C$3:C$200,"S23",PLAN_SEMANAL!F$3:F$200),0) -> 0 | G17: =IFERROR(F17/E17,0) -> 0
A18: AVANCE_POND_GLOBAL | B18: =IFERROR(SUMPRODUCT((AVANCE!A$3:A$206<>"")*AVANCE!G$3:G$206*AVANCE!F$3:F$206)/IFERROR(SUMPRODUCT((AVANCE!A$3:A$206<>"")*AVANCE!G$3:G$206),1),0) -> 0.5784275 | D18: =PLAN_SEMANAL!C6 -> S24 | E18: =IFERROR(SUMIF(PLAN_SEMANAL!C$3:C$200,"S24",PLAN_SEMANAL!E$3:E$200),0) -> 2 | F18: =IFERROR(SUMIF(PLAN_SEMANAL!C$3:C$200,"S24",PLAN_SEMANAL!F$3:F$200),0) -> 1 | G18: =IFERROR(F18/E18,0) -> 0.5
A19: AVANCE_QA | B19: =IFERROR(SUMPRODUCT((AVANCE!C$3:C$206="QA")*AVANCE!G$3:G$206*AVANCE!F$3:F$206)/IFERROR(SUMPRODUCT((AVANCE!C$3:C$206="QA")*AVANCE!G$3:G$206),1),0) -> 0.55555556 | D19: =PLAN_SEMANAL!C7 -> S0 | E19: =IFERROR(SUMIF(PLAN_SEMANAL!C$3:C$200,"S25",PLAN_SEMANAL!E$3:E$200),0) -> 0 | F19: =IFERROR(SUMIF(PLAN_SEMANAL!C$3:C$200,"S25",PLAN_SEMANAL!F$3:F$200),0) -> 0 | G19: =IFERROR(F19/E19,0) -> 0
A20: AVANCE_QC | B20: =IFERROR(SUMPRODUCT((AVANCE!C$3:C$206="QC")*AVANCE!G$3:G$206*AVANCE!F$3:F$206)/IFERROR(SUMPRODUCT((AVANCE!C$3:C$206="QC")*AVANCE!G$3:G$206),1),0) -> 0.59557075 | D20: =PLAN_SEMANAL!C8 -> S0 | E20: =IFERROR(SUMIF(PLAN_SEMANAL!C$3:C$200,"S26",PLAN_SEMANAL!E$3:E$200),0) -> 0 | F20: =IFERROR(SUMIF(PLAN_SEMANAL!C$3:C$200,"S26",PLAN_SEMANAL!F$3:F$200),0) -> 0 | G20: =IFERROR(F20/E20,0) -> 0
A21: NC_ABIERTAS | B21: =IFERROR(COUNTIF('REGISTRO_NC'!I$3:I$201,"🔴 Abierta"),0) -> 2
A22: CERT_ENTREGADOS | B22: =IFERROR(COUNTIF('CERTIFICADOS'!K$3:K$202,"✅ Entregado"),0) -> 8

Sheet INSTRUCCIONES
A1: ⚡ INSTRUCCIONES DE USO — QA/QC PRO Dashboard | Yesid Cruz
A2: 🔄 CÓMO ACTUALIZAR DATOS
A3: Paso 1 | B3: MASTER_ACTIVIDADES: Agregar/editar actividades. Actualizar ESTADO a 'Completo' cuando se termine.
A4: Paso 2 | B4: QC_DETALLE: Actualizar columna EJECUTADO para cada TAG/elemento inspeccionado.
A5: Paso 3 | B5: PLAN_SEMANAL: Agregar filas con FECHA, SEMANA (número), PROYECTO y cantidades.
A6: Paso 4 | B6: Presionar el botón 🔄 en DASHBOARD_PRO para recalcular todo. Ctrl+Alt+F9 también funciona.
A9: ⚙️ MACRO VBA — Código para botón 🔄 ACTUALIZAR
A10: Sub ActualizarDashboard()
A11: ' ── Macro vinculada al botón 🔄 en DASHBOARD_PRO ──
A12: ' Autor: Yesid Cruz — QA/QC PRO Dashboard
A13: Dim ws As Worksheet
A14: Set ws = ThisWorkbook.Sheets("DASHBOARD_PRO")
A16: ' 1. Recalcular todas las fórmulas
A17: Application.CalculateFull
A19: ' 2. Refrescar conexiones (si existen)
A20: ThisWorkbook.RefreshAll
A22: ' 3. Registrar fecha/hora de última actualización
A23: ws.Range("B3").Value = "Dashboard Actualizado por Yesid Cruz el " & _
... A33: 📋 ESTRUCTURA DE HOJAS
A34: MASTER_ACTIVIDADES | B34: Hoja base principal. Registra todas las actividades QA/QC. Fuente única de verdad.
A35: QC_DETALLE | B35: Detalle elemento a elemento de inspecciones (TAG, tipo ensayo, prog/ejec).
A36: AVANCE | B36: Avance consolidado por ID de actividad — alimentado automáticamente.
A37: PLAN_SEMANAL | B37: Programación semanal vs ejecución real. Desviación y % cumplimiento automáticos.
A38: CERTIFICADOS | B38: Control de certificados de calibración y conformidad de materiales.
A39: CONSOLIDADO | B39: Resumen ejecutivo por proyecto con % QA, QC y Total.
A40: CALC_DATA | B40: Tabla auxiliar de KPIs — NO EDITAR MANUALMENTE. Alimenta DASHBOARD_PRO.
A41: REGISTRO_NC | B41: Registro de No Conformidades y seguimiento de acciones correctivas.
